{"video_id": "douyin_6998804603148029221", "wav_result": {"text": "你快点把你的卡给我快点停车了，我给你多待一会儿吗？你快点给我手机截图，照片中的交通违法行为和罚款的项目呢是不存在的。没有往刚讲那里就是这可能能更整齐吧吧，它这个一个接头弄来，把这个具绿中来，必须按这个事情好吃好，是委巴了，然后也也没后悔。", "text_postprocessed": "你 快 点 把 你 的 卡 给 我 快 点 停 车 了 我 给 你 多 待 一 会 儿 吗 你 快 点 给 我 手 机 截 图 照 片 中 的 交 通 违 法 行 为 和 罚 款 的 项 目 呢 是 不 存 在 的 没 有 往 刚 讲 那 里 就 是 这 可 能 能 更 整 齐 吧 吧 它 这 个 一 个 接 头 弄 来 把 这 个 具 绿 中 来 必 须 按 这 个 事 情 好 吃 好 是 委 巴 了 然 后 也 也 没 后 悔", "time_stamp": [[130, 290], [290, 450], [450, 650], [650, 750], [750, 930], [930, 1050], [1050, 1290], [1310, 1510], [1510, 1750], [1770, 1930], [1930, 2150], [2150, 2350], [2350, 2530], [2530, 2770], [2810, 2910], [2910, 2990], [2990, 3130], [3130, 3230], [3230, 3470], [3490, 3590], [3590, 3690], [3690, 3790], [3790, 3950], [3950, 4190], [4270, 4470], [4470, 4710], [4750, 4950], [4950, 5305], [7260, 7500], [7780, 8000], [8000, 8220], [8220, 8440], [8440, 8580], [8580, 8780], [8780, 8900], [8900, 9060], [9060, 9240], [9240, 9360], [9360, 9600], [9860, 10100], [10500, 10720], [10720, 10920], [10920, 11100], [11100, 11300], [11300, 11540], [11640, 11880], [11940, 12180], [12220, 12420], [12420, 12660], [12780, 13020], [13780, 14020], [14200, 14440], [14860, 15100], [15540, 15719], [15719, 15960], [15980, 16120], [16120, 16360], [16560, 16800], [16860, 17040], [17040, 17200], [17200, 17380], [17380, 17500], [17500, 17740], [17740, 17960], [17960, 18100], [18100, 18260], [18260, 18420], [18420, 18620], [18620, 18800], [18800, 19000], [19000, 19180], [19180, 19420], [19480, 19580], [19580, 19680], [19680, 19780], [19780, 19900], [19900, 20100], [20100, 20240], [20240, 20420], [20420, 20560], [20560, 20680], [20680, 20800], [20800, 21040], [21100, 21340], [21340, 21500], [21500, 21720], [21720, 21840], [21840, 22040], [22040, 22180], [22180, 22340], [22340, 22540], [22540, 22700], [22700, 22820], [22820, 22980], [22980, 23405], [24280, 24440], [24440, 24680], [24880, 25040], [25040, 25240], [25240, 25380], [25380, 25500], [25500, 25740], [25880, 26080], [26080, 26320], [26460, 26700], [26760, 26900], [26900, 27020], [27020, 27140], [27140, 27345]], "sentences": [{"text": "你快点把你的卡给我快点停车了,", "start": 130, "end": 2770}, {"text": "我给你多待一会儿吗?", "start": 2770, "end": 3950}, {"text": "你快点给我手机截图,", "start": 3950, "end": 8440}, {"text": "照片中的交通违法行为和罚款的项目呢是不存在的.", "start": 8440, "end": 15719}, {"text": "没有往刚讲那里就是这可能能更整齐吧吧,", "start": 15719, "end": 19420}, {"text": "它这个一个接头弄来,", "start": 19420, "end": 20680}, {"text": "把这个具绿中来,", "start": 20680, "end": 22040}, {"text": "必须按这个事情好吃好,", "start": 22040, "end": 25040}, {"text": "是委巴了,", "start": 25040, "end": 25740}, {"text": "然后也也没后悔.", "start": 25740, "end": 27345}]}, "ocr_result": [{"frame": 0, "result": [["江苏"], ["扬州"], ["官方回应来了!"], ["男子调戏收费员并索要微信"], ["罚款200!"], ["扣6分!"]]}, {"frame": 45, "result": [["你快点把你的卡给我"], ["扣6分"], [""]]}, {"frame": 75, "result": [["我可以和你多待一会吗"]]}, {"frame": 105, "result": [["你快点给我"], ["堵车了"]]}, {"frame": 165, "result": [["男子调戏收费员并索要微信"], ["罚款200!"], ["扣6分"], ["合"]]}, {"frame": 180, "result": [["您还可以处理"], ["1分的违法"], ["1"], ["官方回应:"], ["不存在"], ["F1"], ["江苏扬州3"], ["调戏收费员并索要微信"], ["汤汪收费站出口(沪陕高速G40)"], ["2020-10-0418:10"], ["可款200元"], ["记6分"], ["元"], ["0"], ["逆向行驶"], ["运曲岗"], ["罚款200元"], ["记3分"], ["扬州交警支队宣传科科长:"], ["祝隽"], ["手机截图照片中的交通违法行为"], [""], ["2020-07-27 17:32"], ["罚款100元记2分"]]}, {"frame": 255, "result": [["不按导向车道行驶"], ["开发东路"], ["和罚款的项目"], ["与"]]}, {"frame": 315, "result": [["是不存在的"]]}, {"frame": 330, "result": [["涉事司机:"], ["贾某"], ["抖音上刷的好玩"]]}, {"frame": 345, "result": []}, {"frame": 420, "result": [["弄成扬州的发到朋友圈"]]}, {"frame": 450, "result": [["觉得更真实些吧"]]}, {"frame": 480, "result": [["找收费员并索要微信"], ["收费站出"], ["10-0418:10"], [""], ["陕高速"]]}, {"frame": 555, "result": [["面对现实"], ["一放就行了"]]}, {"frame": 570, "result": [["对现实"], ["晓得这个事情也是违法了"]]}, {"frame": 585, "result": [["现实"]]}, {"frame": 600, "result": [["卫实"], ["把"]]}, {"frame": 615, "result": [["实"], ["把握"]]}, {"frame": 630, "result": [["把握"]]}, {"frame": 645, "result": [["把握未"]]}, {"frame": 660, "result": [["握未来"], ["然后也蛮后悔"]]}], "fps": 25.0}