{"video_id": "douyin_6789943769178311948", "wav_result": {"text": "医生，我可不可以玩你的死呀？我想把球赛踢完，我有答应过妈妈，我会好起来的。如果我死了，她会哭的，我不想要妈妈哭。", "text_postprocessed": "医 生 我 可 不 可 以 玩 你 的 死 呀 我 想 把 球 赛 踢 完 我 有 答 应 过 妈 妈 我 会 好 起 来 的 如 果 我 死 了 她 会 哭 的 我 不 想 要 妈 妈 哭", "time_stamp": [[150, 390], [390, 630], [1010, 1230], [1230, 1390], [1390, 1590], [1590, 1730], [1730, 1870], [1870, 2110], [2130, 2250], [2250, 2430], [2430, 2670], [2730, 3025], [5280, 5440], [5440, 5680], [5700, 5860], [5860, 6040], [6040, 6280], [6300, 6520], [6520, 6760], [7140, 7360], [7360, 7600], [7620, 7760], [7760, 7940], [7940, 8160], [8160, 8360], [8360, 8600], [8940, 9140], [9140, 9340], [9340, 9560], [9560, 9740], [9740, 9960], [9960, 10200], [10560, 10740], [10740, 10940], [10940, 11180], [11180, 11420], [11460, 11700], [12000, 12180], [12180, 12420], [12440, 12680], [12700, 12940], [13380, 13600], [13600, 13780], [13780, 13960], [13960, 14200], [14380, 14560], [14560, 14740], [14740, 15005]], "sentences": [{"text": "医生,", "start": 150, "end": 630}, {"text": "我可不可以玩你的死呀?", "start": 630, "end": 3025}, {"text": "我想把球赛踢完,", "start": 3025, "end": 6760}, {"text": "我有答应过妈妈,", "start": 6760, "end": 8600}, {"text": "我会好起来的.", "start": 8600, "end": 10200}, {"text": "如果我死了,", "start": 10200, "end": 11700}, {"text": "她会哭的,", "start": 11700, "end": 12940}, {"text": "我不想要妈妈哭.", "start": 12940, "end": 15005}]}, "ocr_result": [{"frame": 0, "result": []}, {"frame": 15, "result": [["医生,我可不可以晚点死啊!"], ["!!"]]}, {"frame": 30, "result": [["医生,"], ["我可不可以晚点死啊!"], [","]]}, {"frame": 45, "result": []}, {"frame": 75, "result": []}, {"frame": 105, "result": []}, {"frame": 150, "result": []}, {"frame": 180, "result": [["我想把球赛踢完"]]}, {"frame": 225, "result": [["我有答应过妈妈!"]]}, {"frame": 270, "result": []}, {"frame": 300, "result": [["我会好起来的!"]]}, {"frame": 360, "result": [[""], ["如果我死了"]]}, {"frame": 390, "result": [["她会哭的,"], ["我不想让妈妈哭"]]}, {"frame": 480, "result": [["她"], ["妈哭"]]}], "fps": 30.00030000300003}