{"video_id": "douyin_6650290449728720132", "wav_result": {"text": "嗯。", "text_postprocessed": "嗯", "time_stamp": [[210, 450]], "sentences": [{"text": "嗯.", "start": 210, "end": 450}]}, "ocr_result": [{"frame": 0, "result": [["林青霞和秦汉"], ["结婚了?"], ["林青霞和秦汉结婚了???这是什么世纪大新闻盒盘盘好低调啊,感觉一大波讨"], ["论即将来袭"], ["#林青霞#"], ["土收起"], ["Q查看大图"], ["●向左旋转"], ["Sup"], ["後来搬到香港"], ["72歲秦漢宣布大婚,林青霞承"], ["認低調領證,25年後兩人終於..."]]}, {"frame": 45, "result": [["土收起"], ["SUPER"], [""], ["72歲秦漢宣布大婚,"], ["林青霞承"]]}, {"frame": 75, "result": [["OUPER"], ["U"], ["="], ["士"], ["小千"], ["+丰品"]]}, {"frame": 105, "result": [["後来搬到香港"]]}, {"frame": 135, "result": [["这是什么"], ["世纪大新闻"], ["秦汉与林青霞"]]}, {"frame": 255, "result": [["好低调啊"]]}, {"frame": 345, "result": []}, {"frame": 375, "result": [["感觉一大波"], ["讨论即将来袭"], ["林青霞秦漢宣布大婚,這場婚禮"], ["林青霞秦漢"], ["林青霞等了25年,兩人終於牽..."], ["13:31大婚"], ["YouTube-3天前"], ["林青霞秦漢同時發文承認私生"], ["子,當年分手真相遭曝光,林..."], ["11:54"], ["如果林青霞离婚了,她真的会和"], ["秦汉复合么?"], ["18:28"], ["YouTube-2018年10月2日"]]}, {"frame": 435, "result": [["3"], ["LO%"], ["72歲秦漢宣布大婚,林青霞承認"], ["72歲秦漢宣布大婚"], ["低調領證,25年後兩人終於有..."], ["8:43"], ["承認已领橙"]]}, {"frame": 450, "result": [["人"], ["MO"], ["8:43"], ["曝林青霞与秦汉分手内幕:秦汉"]]}, {"frame": 465, "result": [["承認已领橙"], ["跪地哭求"], ["3:45"], ["110"]]}, {"frame": 480, "result": [["TH"]]}, {"frame": 495, "result": [["18:28"], ["林青霞秦漢私生子曝光,時隔3個"], ["表"], ["蓬壮青霞"], ["月,林青霞離婚真實原因外泄?"]]}, {"frame": 510, "result": [["第"]]}, {"frame": 570, "result": [["第"]]}, {"frame": 600, "result": [["第"]]}], "fps": 25.0}