{"video_id": "douyin_7009653416536313088", "wav_result": {"text": "这可怎么整啊，绿地着火了。这可怎么办？嗯，这个怎么上去啊，问题是。", "text_postprocessed": "这 可 怎 么 整 啊 绿 地 着 火 了 这 可 怎 么 办 嗯 这 个 怎 么 上 去 啊 问 题 是", "time_stamp": [[110, 250], [250, 370], [370, 470], [470, 590], [590, 810], [810, 1135], [1800, 2000], [2000, 2240], [2260, 2400], [2400, 2640], [2700, 2940], [3300, 3460], [3460, 3580], [3580, 3679], [3679, 3800], [3800, 4155], [5420, 5710], [7260, 7399], [7399, 7520], [7520, 7620], [7620, 7760], [7760, 8000], [8020, 8140], [8140, 8280], [8280, 8360], [8360, 8540], [8540, 8865]], "sentences": [{"text": "这可怎么整啊,", "start": 110, "end": 1135}, {"text": "绿地着火了.", "start": 1135, "end": 2940}, {"text": "这可怎么办?", "start": 2940, "end": 4155}, {"text": "嗯,", "start": 4155, "end": 5710}, {"text": "这个怎么上去啊,", "start": 5710, "end": 8280}, {"text": "问题是.", "start": 8280, "end": 8865}]}, "ocr_result": [{"frame": 0, "result": []}, {"frame": 15, "result": [["这可怎么整啊"]]}, {"frame": 45, "result": []}, {"frame": 75, "result": [["缘地着火7"]]}, {"frame": 105, "result": [["经核实"], ["网友拍摄的"], ["疑似济南缘地普利中心着火"], ["W"], ["实为下雨后产生的雾气"], ["请市民不必惊慌"]]}, {"frame": 120, "result": []}, {"frame": 270, "result": [["W"]]}], "fps": 30.0}