{"video_id": "douyin_6961724093309668641", "wav_result": {"text": "你看平天我也自己捞狱，自己村坚守是通经过公安机关调查。实际上这段这段视频呢就是一个谣言，心里很气愤。对啊，希望公安机关能尽快调查清楚，把我们清白了。如果发现我们有的违规或者违违疑疑惑，我我们管管工作员呢当面向来当面解释清楚，我不能随意的就是说想发什么就发么么生改我们单位的现象，我们护管的这个声誉。", "text_postprocessed": "你 看 平 天 我 也 自 己 捞 狱 自 己 村 坚 守 是 通 经 过 公 安 机 关 调 查 实 际 上 这 段 这 段 视 频 呢 就 是 一 个 谣 言 心 里 很 气 愤 对 啊 希 望 公 安 机 关 能 尽 快 调 查 清 楚 把 我 们 清 白 了 如 果 发 现 我 们 有 的 违 规 或 者 违 违 疑 疑 惑 我 我 们 管 管 工 作 员 呢 当 面 向 来 当 面 解 释 清 楚 我 不 能 随 意 的 就 是 说 想 发 什 么 就 发 么 么 生 改 我 们 单 位 的 现 象 我 们 护 管 的 这 个 声 誉", "time_stamp": [[2300, 2460], [2460, 2580], [2580, 2739], [2739, 2860], [2860, 3020], [3020, 3260], [3420, 3620], [3620, 3800], [3800, 3960], [3960, 4525], [5450, 5610], [5610, 5850], [5850, 5970], [5970, 6170], [6170, 6410], [6450, 6690], [7470, 7650], [7650, 7810], [7810, 8050], [8090, 8330], [8370, 8490], [8490, 8650], [8650, 8750], [8750, 8990], [9050, 9190], [9190, 9330], [9330, 9470], [9470, 9710], [9730, 9910], [9910, 10030], [10030, 10170], [10170, 10270], [10270, 10370], [10370, 10490], [10490, 10590], [10590, 10710], [10710, 10930], [10930, 11090], [11090, 11250], [11250, 11350], [11350, 11470], [11470, 11710], [12590, 12750], [12750, 12990], [13070, 13310], [13910, 14030], [14030, 14150], [14150, 14250], [14250, 14410], [14410, 14570], [14570, 14730], [14730, 14970], [15590, 15770], [15770, 16009], [16410, 16530], [16530, 16690], [16690, 16790], [16790, 16970], [16970, 17090], [17090, 17330], [17450, 17610], [17610, 17850], [17850, 18050], [18050, 18170], [18170, 18410], [18450, 18630], [18630, 18770], [18770, 19009], [19190, 19370], [19370, 19610], [20110, 20310], [20310, 20470], [20470, 20630], [20630, 20750], [20750, 20850], [20850, 20970], [20970, 21090], [21090, 21330], [21369, 21590], [21590, 21830], [21890, 22130], [22369, 22570], [22570, 22790], [22790, 23030], [23270, 23410], [23410, 23530], [23530, 23710], [23710, 23950], [24450, 24610], [24610, 24730], [24730, 24850], [24850, 24950], [24950, 25070], [25070, 25170], [25170, 25310], [25310, 25430], [25430, 25549], [25549, 25790], [26030, 26189], [26189, 26330], [26330, 26470], [26470, 26590], [26590, 26710], [26710, 26810], [26810, 26930], [26930, 27170], [27189, 27350], [27350, 27450], [27450, 27590], [27590, 27710], [27710, 27850], [27850, 27950], [27950, 28049], [28049, 28150], [28150, 28270], [28270, 28450], [28450, 28570], [28570, 28670], [28670, 28770], [28770, 28890], [28890, 29049], [29049, 29210], [29210, 29330], [29330, 29509], [29509, 29610], [29610, 29730], [29730, 29869], [29869, 29970], [29970, 30110], [30110, 30210], [30210, 30330], [30330, 30430], [30430, 30670], [30710, 30950], [30950, 31170], [31170, 31270], [31270, 31369], [31369, 32275]], "sentences": [{"text": "你看平天我也自己捞狱,", "start": 2300, "end": 4525}, {"text": "自己村坚守是通经过公安机关调查.", "start": 4525, "end": 9190}, {"text": "实际上这段这段视频呢就是一个谣言,", "start": 9190, "end": 11470}, {"text": "心里很气愤.", "start": 11470, "end": 14030}, {"text": "对啊,", "start": 14030, "end": 14250}, {"text": "希望公安机关能尽快调查清楚,", "start": 14250, "end": 17610}, {"text": "把我们清白了.", "start": 17610, "end": 18770}, {"text": "如果发现我们有的违规或者违违疑疑惑,", "start": 18770, "end": 23030}, {"text": "我我们管管工作员呢当面向来当面解释清楚,", "start": 23030, "end": 26710}, {"text": "我不能随意的就是说想发什么就发么么生改我们单位的现象,", "start": 26710, "end": 30110}, {"text": "我们护管的这个声誉.", "start": 30110, "end": 32275}]}, "ocr_result": [{"frame": 0, "result": [["池州广播电视台"], ["视频来源于网络"]]}, {"frame": 15, "result": []}, {"frame": 30, "result": []}, {"frame": 45, "result": []}, {"frame": 90, "result": [["平天湖湖管监守自盗"], ["违规捕鱼"], ["平天湖管理员自己捕鱼"]]}, {"frame": 105, "result": [["违规捕鱼?"]]}, {"frame": 120, "result": []}, {"frame": 135, "result": []}, {"frame": 165, "result": [["三"]]}, {"frame": 195, "result": [["这算监守自盗吧"]]}, {"frame": 225, "result": [["平天湖湖管监自盗"], ["随注合?"], ["经过公安机关调查"]]}, {"frame": 240, "result": []}, {"frame": 270, "result": [["可"], ["径流、补充"], ["生态系统"], ["美"], ["地下水、改"], ["和"], ["批"], ["m"], ["所不能替代"], ["区域"], ["外)"], ["地公约》的定义已"], ["地的定义还"], ["港批智夹"], ["由接受"], ["其为天然或人工、常"], ["湿原、泥炭地或水域"], ["的成"], ["动的、"], ["的水体"], ["为读"], [""], ["医用"], ["本沼"], ["|阁"], ["以"]]}, {"frame": 330, "result": [["心里很气愤"], ["这就是诬陷我们"]]}, {"frame": 360, "result": []}, {"frame": 450, "result": [["我们湖管是正常巡湖打捞垃圾"]]}, {"frame": 495, "result": [["希望公安机关尽快调查清楚"]]}, {"frame": 510, "result": []}, {"frame": 540, "result": []}, {"frame": 555, "result": []}, {"frame": 600, "result": [["如果发现我们有违规"]]}, {"frame": 630, "result": [["多报编"], ["CZT"]]}, {"frame": 690, "result": [["多推度"], ["CZV"], ["或者有疑惑的"], ["句"]]}, {"frame": 705, "result": [["多推度"], ["CZTV"], ["你可以随时叫我们湖管工作人员"]]}, {"frame": 750, "result": [["池州广播电视台"], ["据了解"], ["公"], ["ZTV"]]}, {"frame": 765, "result": [["公安机关已对造谣人"]]}, {"frame": 780, "result": [["进行了批评"], ["C"]]}, {"frame": 795, "result": [["公安机关已对造谣人员"], ["进行了批评教育"], ["当面解释清楚"]]}, {"frame": 825, "result": [["视频来源于网络"], ["而不是随意的想发什么就发什么"]]}, {"frame": 840, "result": []}, {"frame": 900, "result": [["来损害我们单位形象和湖管的声誉"]]}, {"frame": 915, "result": []}, {"frame": 930, "result": []}, {"frame": 945, "result": []}, {"frame": 960, "result": [["关注"], ["U"], ["点赞"], ["池州广播电视台"]]}, {"frame": 975, "result": []}], "fps": 30.0}