{"video_id": "douyin_6791821286776507648", "wav_result": {"text": "好怪哟，你有那么坏的人呢，硬是这世界上真的想不到，有那么坏的人。", "text_postprocessed": "好 怪 哟 你 有 那 么 坏 的 人 呢 硬 是 这 世 界 上 真 的 想 不 到 有 那 么 坏 的 人", "time_stamp": [[640, 880], [899, 1140], [1360, 1875], [2639, 2760], [2760, 2900], [2900, 2980], [2980, 3179], [3179, 3400], [3400, 3580], [3580, 3820], [3860, 4100], [4160, 4340], [4340, 4500], [4500, 4680], [4680, 4820], [4820, 5060], [5060, 5300], [5760, 5880], [5880, 6060], [6060, 6180], [6180, 6300], [6300, 6400], [6400, 6540], [6540, 6640], [6640, 6780], [6780, 7000], [7000, 7240], [7240, 7415]], "sentences": [{"text": "好怪哟,", "start": 640, "end": 1875}, {"text": "你有那么坏的人呢,", "start": 1875, "end": 4100}, {"text": "硬是这世界上真的想不到,", "start": 4100, "end": 6400}, {"text": "有那么坏的人.", "start": 6400, "end": 7415}]}, "ocr_result": [{"frame": 0, "result": [["近日重庆江北"], ["一位穿红色棉袄的大妈"], ["乘电梯不仅不戴口罩"], ["还故意在电梯按钮上"], ["狂吐多次口水"]]}, {"frame": 15, "result": []}, {"frame": 75, "result": [["近日"], ["重庆江北"], ["市民:好坏哟"]]}, {"frame": 105, "result": [["真的有这么坏的人呐"]]}, {"frame": 120, "result": [["小区保安看到后"], ["合力将其扭送到派出所"]]}, {"frame": 135, "result": [["7"], ["真的有这么坏的人呐"]]}, {"frame": 150, "result": [["世界上"]]}, {"frame": 165, "result": []}, {"frame": 240, "result": [["据警方通报"], ["女子自称与他人发生纠纷心生怨恨"], ["在电梯内吐唾沫泄愤"], ["经查其14天内无外地居住史,"], ["未接触湖北地区人员"], ["体温正常,"], ["目前已被刑拘"]]}, {"frame": 255, "result": []}, {"frame": 270, "result": []}, {"frame": 285, "result": []}, {"frame": 300, "result": []}, {"frame": 315, "result": [["21:"]]}, {"frame": 330, "result": [[""]]}, {"frame": 345, "result": []}, {"frame": 360, "result": []}, {"frame": 375, "result": []}], "fps": 29.0}