{"video_id": "douyin_6864470920677936399", "wav_result": {"text": "还是蜃楼？还是蜃楼？唉，海市蜃楼味海市蜃楼，哎，阿托第一次看见。", "text_postprocessed": "还 是 蜃 楼 还 是 蜃 楼 唉 海 市 蜃 楼 味 海 市 蜃 楼 哎 阿 托 第 一 次 看 见", "time_stamp": [[4000, 4080], [4080, 4260], [4260, 4360], [4360, 4600], [4860, 5060], [5060, 5260], [5260, 5460], [5460, 5580], [5580, 5965], [7860, 8000], [8000, 8120], [8120, 8300], [8300, 8420], [8420, 8660], [9280, 9480], [9480, 9660], [9660, 9840], [9840, 9940], [9940, 10180], [10200, 10300], [10300, 10540], [10800, 10880], [10880, 11000], [11000, 11140], [11140, 11300], [11300, 11505]], "sentences": [{"text": "还是蜃楼?", "start": 4000, "end": 4600}, {"text": "还是蜃楼?", "start": 4600, "end": 5580}, {"text": "唉,", "start": 5580, "end": 5965}, {"text": "海市蜃楼味海市蜃楼,", "start": 5965, "end": 9940}, {"text": "哎,", "start": 9940, "end": 10180}, {"text": "阿托第一次看见.", "start": 10180, "end": 11505}]}, "ocr_result": [{"frame": 0, "result": [["上海上空现海市蜃楼?"], ["PE"], ["气象局:"], ["系罕见"], ["物影上投"], ["“g"], ["没”"], ["现象"]]}, {"frame": 30, "result": [["“"], ["出"]]}, {"frame": 60, "result": [["科授节"], ["没”"]]}, {"frame": 75, "result": [["上"], ["科技"], ["“物影上投”"]]}, {"frame": 90, "result": []}, {"frame": 135, "result": [["上海"], ["科技节"], ["看一下那个"], ["“物影上投"]]}, {"frame": 150, "result": [["上海"], ["科技节"]]}, {"frame": 180, "result": [["系罕见“物影上投"]]}, {"frame": 225, "result": [["是不是海市蜃楼"], ["決佳"], ["道"], ["“物影上投”"]]}, {"frame": 345, "result": []}, {"frame": 375, "result": [["上海上空现海市蜃楼?"], ["OL"], ["技节"], ["嗯是海市蜃楼那个叫海市蜃楼哎"]]}, {"frame": 420, "result": [["区安河南"], ["隧道南路"]]}, {"frame": 465, "result": []}, {"frame": 510, "result": []}, {"frame": 555, "result": [["海市蜃楼哎阿冲"]]}, {"frame": 585, "result": [["系罕见“!"]]}, {"frame": 615, "result": []}, {"frame": 645, "result": [["上海上空现海市蜃楼?"], ["第一次看见"]]}, {"frame": 690, "result": []}], "fps": 60.0}