{"video_id": "douyin_6792441400697867534", "wav_result": {"text": "你干嘛？我听说香油滴在鼻孔里可以防止病毒传播。我在帮你滴香油。嗯，香油在鼻子里走个过场，既阻隔不了病毒进来，也没有办法阻止病毒繁衍。除了身上满满的都是香油味儿，什么效果，也不会有能有效灭活新型冠状病毒的物质乙醚百分之七十五乙醇含氯消毒剂、过氧乙酸氯仿这些脂溶剂。", "text_postprocessed": "你 干 嘛 我 听 说 香 油 滴 在 鼻 孔 里 可 以 防 止 病 毒 传 播 我 在 帮 你 滴 香 油 嗯 香 油 在 鼻 子 里 走 个 过 场 既 阻 隔 不 了 病 毒 进 来 也 没 有 办 法 阻 止 病 毒 繁 衍 除 了 身 上 满 满 的 都 是 香 油 味 儿 什 么 效 果 也 不 会 有 能 有 效 灭 活 新 型 冠 状 病 毒 的 物 质 乙 醚 百 分 之 七 十 五 乙 醇 含 氯 消 毒 剂 过 氧 乙 酸 氯 仿 这 些 脂 溶 剂", "time_stamp": [[2530, 2650], [2650, 2750], [2750, 2989], [3090, 3250], [3250, 3349], [3349, 3469], [3469, 3590], [3590, 3690], [3690, 3809], [3809, 3889], [3889, 3989], [3989, 4109], [4109, 4350], [4350, 4430], [4430, 4510], [4510, 4590], [4590, 4689], [4689, 4810], [4810, 4949], [4949, 5050], [5050, 5290], [5410, 5510], [5510, 5630], [5630, 5750], [5750, 5870], [5870, 6010], [6010, 6170], [6170, 6410], [6590, 6915], [7710, 7870], [7870, 8050], [8050, 8230], [8230, 8390], [8390, 8490], [8490, 8630], [8630, 8750], [8750, 8850], [8850, 8930], [8930, 9170], [9190, 9370], [9370, 9470], [9470, 9550], [9550, 9650], [9650, 9770], [9770, 9890], [9890, 10010], [10010, 10130], [10130, 10370], [10370, 10490], [10490, 10570], [10570, 10670], [10670, 10750], [10750, 10910], [10910, 11010], [11010, 11110], [11110, 11190], [11190, 11310], [11310, 11430], [11430, 11670], [11810, 11910], [11910, 11990], [11990, 12090], [12090, 12210], [12210, 12330], [12330, 12510], [12510, 12590], [12590, 12670], [12670, 12770], [12770, 12850], [12850, 12930], [12930, 13050], [13050, 13230], [13230, 13470], [13470, 13590], [13590, 13670], [13670, 13770], [13770, 13890], [13890, 13970], [13970, 14050], [14050, 14250], [14250, 14470], [14470, 14590], [14590, 14730], [14730, 14890], [14890, 15050], [15050, 15190], [15190, 15330], [15330, 15430], [15430, 15570], [15570, 15670], [15670, 15790], [15790, 15930], [15930, 16090], [16090, 16329], [16350, 16509], [16509, 16690], [16690, 16770], [16770, 16870], [16870, 16950], [16950, 17030], [17030, 17150], [17150, 17270], [17270, 17390], [17390, 17630], [17630, 17710], [17710, 17810], [17810, 17930], [17930, 18009], [18009, 18130], [18130, 18230], [18230, 18310], [18310, 18410], [18410, 18590], [18590, 18710], [18710, 18950], [18970, 19070], [19070, 19250], [19250, 19370], [19370, 19550], [19550, 19755]], "sentences": [{"text": "你干嘛?", "start": 2530, "end": 2989}, {"text": "我听说香油滴在鼻孔里可以防止病毒传播.", "start": 2989, "end": 5290}, {"text": "我在帮你滴香油.", "start": 5290, "end": 6410}, {"text": "嗯,", "start": 6410, "end": 6915}, {"text": "香油在鼻子里走个过场,", "start": 6915, "end": 9170}, {"text": "既阻隔不了病毒进来,", "start": 9170, "end": 10370}, {"text": "也没有办法阻止病毒繁衍.", "start": 10370, "end": 11670}, {"text": "除了身上满满的都是香油味儿,", "start": 11670, "end": 13230}, {"text": "什么效果,", "start": 13230, "end": 13770}, {"text": "也不会有能有效灭活新型冠状病毒的物质乙醚百分之七十五乙醇含氯消毒剂过氧乙酸氯仿这些脂溶剂.", "start": 13770, "end": 19755}]}, "ocr_result": [{"frame": 0, "result": [["主播捉"], ["金记"], ["中国蓝融媒·93TV"]]}, {"frame": 60, "result": []}, {"frame": 105, "result": [["谣"], ["记"], ["我听说香油滴在鼻孔里"]]}, {"frame": 135, "result": [["可以防止病毒传播"]]}, {"frame": 150, "result": []}, {"frame": 180, "result": [["我在帮你滴香油"]]}, {"frame": 195, "result": []}, {"frame": 210, "result": [["爱"]]}, {"frame": 225, "result": [["假的!"]]}, {"frame": 240, "result": [["香油在鼻子里走个过场"]]}, {"frame": 255, "result": []}, {"frame": 270, "result": []}, {"frame": 285, "result": [["既阻隔不了病毒进来"], ["凯"]]}, {"frame": 300, "result": [["既阻隔不了病毒进来"], ["织"]]}, {"frame": 315, "result": [["也没有办法阻止病毒繁衍"]]}, {"frame": 330, "result": []}, {"frame": 360, "result": [["除了身上满满的都是香油"]]}, {"frame": 375, "result": []}, {"frame": 390, "result": [["什么效果也不会有"]]}, {"frame": 405, "result": []}, {"frame": 435, "result": [["能有效灭活"], ["新型冠状病毒的物质"]]}, {"frame": 495, "result": [["乙醚"]]}, {"frame": 510, "result": [["75%Z醇"]]}, {"frame": 540, "result": [["含氧消毒剂"]]}, {"frame": 555, "result": [["过氧乙酸"]]}], "fps": 30.0}