{"video_id": "douyin_6952110582992538893", "wav_result": {"text": "我要娘娘用你手机这么多人啊，啥都过不去，俺就说把面子给爸完了，你给人家走，这这边这都撒单子，真相。原来是这样，滚go就在了那一生，把每个黑暗的地方全部都照亮。当时光像男儿的胸膛。", "text_postprocessed": "我 要 娘 娘 用 你 手 机 这 么 多 人 啊 啥 都 过 不 去 俺 就 说 把 面 子 给 爸 完 了 你 给 人 家 走 这 这 边 这 都 撒 单 子 真 相 原 来 是 这 样 滚 go 就 在 了 那 一 生 把 每 个 黑 暗 的 地 方 全 部 都 照 亮 当 时 光 像 男 儿 的 胸 膛", "time_stamp": [[4830, 4930], [4930, 5090], [5090, 5229], [5229, 5390], [5390, 5569], [5569, 5689], [5689, 5790], [5790, 5949], [5949, 6090], [6090, 6250], [6250, 6430], [6430, 6609], [6609, 6785], [7770, 7869], [7869, 8010], [8010, 8189], [8189, 8350], [8350, 8590], [9090, 9190], [9190, 9309], [9309, 9430], [9430, 9549], [9549, 9670], [9670, 9770], [9770, 9910], [9910, 10010], [10010, 10129], [10129, 10309], [10309, 10490], [10490, 10590], [10590, 10670], [10670, 10830], [10830, 10969], [10969, 11110], [11110, 11270], [11270, 11450], [11450, 11570], [11570, 11750], [11750, 11870], [11870, 12070], [12070, 12309], [12970, 13130], [13130, 13310], [13310, 13410], [13410, 13510], [13510, 13710], [13710, 13790], [13790, 14055], [15080, 15260], [15260, 15500], [17700, 17940], [18000, 18220], [18220, 18380], [18380, 18555], [19080, 19320], [19360, 19605], [20500, 20660], [20660, 20900], [21040, 21255], [21840, 22080], [22120, 22360], [22480, 22720], [22780, 23020], [23060, 23300], [23640, 23880], [23940, 24180], [24240, 24480], [24700, 24940], [25060, 25265], [27160, 27400], [27720, 27960], [28140, 28535], [29450, 29690], [29710, 29950], [29970, 30210], [30250, 30490], [30770, 31009], [31130, 31485]], "sentences": [{"text": "我要娘娘用你手机这么多人啊,", "start": 4830, "end": 6785}, {"text": "啥都过不去,", "start": 6785, "end": 8590}, {"text": "俺就说把面子给爸完了,", "start": 8590, "end": 10309}, {"text": "你给人家走,", "start": 10309, "end": 10969}, {"text": "这这边这都撒单子,", "start": 10969, "end": 12309}, {"text": "真相.", "start": 12309, "end": 13310}, {"text": "原来是这样,", "start": 13310, "end": 14055}, {"text": "滚go就在了那一生,", "start": 14055, "end": 19605}, {"text": "把每个黑暗的地方全部都照亮.", "start": 19605, "end": 25265}, {"text": "当时光像男儿的胸膛.", "start": 25265, "end": 31485}]}, "ocr_result": [{"frame": 0, "result": [["警普情通报"], ["2021年4月17日,武都区公安局接网民举报"], ["抖音中有群众发布\"兰天广场铜人被推倒”"], ["'一"], ["短视频,举报群众向警方求证,视频内容是"], ["否属实,破坏分子是否被查处。"], ["武都区公安局接举报后,立即开展调查,经"], ["核查该铜人倒地不是人为故意损坏的,而是"], ["该铜人常年暴露在露天,“小铜人\"底桩由一"], ["根铁管固定,因时间较久遭到腐蚀,已发生"], ["倾斜要倒,根据调取周边监控视频查看,过"], ["路的两年轻男子想要扶正,但\"小铜人\"自身"], ["的重量大,反而断裂倒地,断裂倒地当时时"], ["间尚早,过路的人也多,应该排除故意损坏"], ["的可能。"], ["武都区公安局"], ["2021年4月17日"]]}, {"frame": 15, "result": [["警情通报"]]}, {"frame": 30, "result": []}, {"frame": 135, "result": [["2021年4月17日,武都区公安局"], ["“兰天广场铜人被推倒”一短视频"], ["接网民举报,抖音中有群众发布"], ["举报群众向警方求证,视频内容"], ["是否属实,破坏份子是否被查处。"]]}, {"frame": 150, "result": []}, {"frame": 165, "result": []}, {"frame": 180, "result": []}, {"frame": 195, "result": []}, {"frame": 210, "result": []}, {"frame": 225, "result": []}, {"frame": 240, "result": [["“兰天广场铜人被推倒”一短视频"]]}, {"frame": 255, "result": []}, {"frame": 270, "result": []}, {"frame": 285, "result": []}, {"frame": 300, "result": []}, {"frame": 315, "result": []}, {"frame": 330, "result": []}, {"frame": 345, "result": []}, {"frame": 360, "result": [["2021年4月17日,武都区公安局"]]}, {"frame": 375, "result": []}, {"frame": 390, "result": [["真相原来是这样"], ["通过调取现场监控发现"], ["小铜人”因支撑柱腐朽"], ["“)"], ["发生严重倾斜,现场围观"], ["群众较多"]]}, {"frame": 420, "result": []}, {"frame": 450, "result": [["真相原来是这样"]]}, {"frame": 465, "result": [["两名热心群众想要帮助扶正"], ["但腐朽的支柱因“小铜人”过重"], ["自行断裂倒地"]]}, {"frame": 495, "result": [["真相"], ["原来是这样"]]}, {"frame": 540, "result": []}, {"frame": 645, "result": []}, {"frame": 690, "result": []}, {"frame": 795, "result": []}, {"frame": 855, "result": []}, {"frame": 900, "result": []}, {"frame": 930, "result": []}, {"frame": 960, "result": []}], "fps": 30.0}