{"video_id": "douyin_6922657004334943495", "wav_result": {"text": "在市场上买了两斤鱿鱼，拿回开水一趟，没了，鱿鱼买回来了，今天是五分半，然后看一下已经跟昨天那个状态差不多了，已经完全成汤。", "text_postprocessed": "在 市 场 上 买 了 两 斤 鱿 鱼 拿 回 开 水 一 趟 没 了 鱿 鱼 买 回 来 了 今 天 是 五 分 半 然 后 看 一 下 已 经 跟 昨 天 那 个 状 态 差 不 多 了 已 经 完 全 成 汤", "time_stamp": [[190, 370], [370, 530], [530, 650], [650, 850], [850, 950], [950, 1090], [1090, 1310], [1310, 1510], [1510, 1670], [1670, 1910], [2510, 2690], [2690, 2890], [2890, 3050], [3050, 3230], [3230, 3330], [3330, 3570], [3750, 3990], [3990, 4230], [5370, 5610], [5610, 5810], [5810, 5970], [5970, 6090], [6090, 6270], [6270, 6510], [7410, 7590], [7590, 7770], [7770, 8010], [8050, 8290], [8310, 8550], [8550, 8790], [9070, 9210], [9210, 9410], [9410, 9590], [9590, 9690], [9690, 9930], [10910, 11070], [11070, 11310], [11310, 11510], [11510, 11670], [11670, 11810], [11810, 11910], [11910, 12010], [12010, 12150], [12150, 12390], [12410, 12570], [12570, 12690], [12690, 12870], [12870, 13070], [13070, 13230], [13230, 13470], [13530, 13730], [13730, 13970], [13990, 14210], [14210, 14450]], "sentences": [{"text": "在市场上买了两斤鱿鱼,", "start": 190, "end": 1910}, {"text": "拿回开水一趟,", "start": 1910, "end": 3570}, {"text": "没了,", "start": 3570, "end": 4230}, {"text": "鱿鱼买回来了,", "start": 4230, "end": 6510}, {"text": "今天是五分半,", "start": 6510, "end": 8790}, {"text": "然后看一下已经跟昨天那个状态差不多了,", "start": 8790, "end": 13070}, {"text": "已经完全成汤.", "start": 13070, "end": 14450}]}, "ocr_result": [{"frame": 0, "result": [["鱿鱼开水煮水后消失不见"], ["网友:"], ["这是什么魔术?"], ["1月27日"], ["四川"], ["成都"], ["神鸟"], ["知讯"]]}, {"frame": 15, "result": []}, {"frame": 30, "result": []}, {"frame": 45, "result": []}, {"frame": 60, "result": [["新"], ["专"], ["干"], ["发"]]}, {"frame": 75, "result": [["一女子称在市场上买了2斤鱿鱼"], ["回家一焯水,就没了"]]}, {"frame": 90, "result": []}, {"frame": 105, "result": []}, {"frame": 120, "result": []}, {"frame": 135, "result": []}, {"frame": 150, "result": [["女子商视频发"], ["到欣"], ["aV"]]}, {"frame": 165, "result": [["女子将视频发到网上引发质疑后"], ["她再次从市场购买鱿鱼"], ["用相同方法试验"], ["CW"]]}, {"frame": 195, "result": []}, {"frame": 210, "result": []}, {"frame": 225, "result": []}, {"frame": 240, "result": [["05:36 04"]]}, {"frame": 270, "result": []}, {"frame": 285, "result": []}, {"frame": 300, "result": []}, {"frame": 315, "result": [["融化了。这属于化学还是物理?"], ["56分钟前"], ["回复"]]}, {"frame": 330, "result": [["T"]]}, {"frame": 345, "result": []}, {"frame": 360, "result": [["融化了。这属于化学还是物理?"], ["56分钟前"], ["回复"]]}, {"frame": 375, "result": [["56分钟前"]]}, {"frame": 390, "result": [["S"], ["几乎完全成水"]]}, {"frame": 420, "result": [["几乎完全成水"], ["真鱿鱼,只不过不新鲜还放了不少保鲜剂"], ["1小时前"]]}, {"frame": 435, "result": [["真鱿鱼,"], ["只不过不新鲜还放了不少保鲜齐"]]}, {"frame": 450, "result": [["专家分析原因"], ["或为食材本身已不新鲜"], ["市场"], ["成都市场监管食食元"], ["十关注"], ["1-27 21:54"], ["【#专家分析市民购鱿鱼焯水后离奇消失#或为食材本"], ["身已不新鲜】近日,一段成都市民购买#2斤鱿鱼焯水"], ["后离奇消失#的视频引发关注,女子为证明自己没说"], ["谎,又去买了一些鱿鱼,并用同样的方法焯水,5-8"], ["分钟后只能捞起些许碎渣。对此,中国农业大学食品"], ["学院副教授朱毅告诉四川手机报,最大的可能是鱿鱼"], ["被反复解冻后导致细胞被破坏,细胞中的液体流出,"], ["食材新鲜度下降,在生物学上叫“冻融”。加上长时间"], ["蒸煮,视觉上产生了“化”的感觉,海参等水产品也会"], ["有这种现象。此外,食材中的细菌腐烂、食材在大量"], ["吸水泡发后长时间蒸煮,也会导致“融化”。对于是否"], ["有“胶水制作鱿鱼”的可能性,朱教授表示,成本高且"], ["技术上难以实现。(记者徐浩煊)口四川手机报的微"], ["博视频"], ["神鸟"], ["知讯"]]}, {"frame": 465, "result": [["专家分析原因:"], ["成都"], ["市场监管"], ["成都市场监管"], ["十关注"], ["1-27 21:54"], ["身已不新鲜】近日"], ["一段成都市民购买#2斤鱿鱼焯水"], ["学院副教授朱毅告诉四川手机报,最大的可能是鱿鱼"], ["有这种现象。此外,食材中的细菌腐烂、食材在大量"], ["技术上难以实现。"], ["(记者徐浩煊)"], ["口四川手机报的微"], ["博视频"], ["询"]]}], "fps": 30.0}