{"video_id": "douyin_6935673902374997278", "wav_result": {"text": "二月五日下午，在南宁市大学东路西往东方向，一辆白色宝马轿车，因司机操作不当冲撞公交站台，导致两名候车老人受伤。三月二日，记者了解到，其中一名七十七岁的伤者经抢救无效，已经不幸离世。事故发生在当天上午十点四十一分左右，肇事车辆冲撞。南宁市大学科园路口公交站台，导致两名老人受伤。送医受害者家属罗先生，老人的两个脚都是骨头外露。当天下午三点钟进了手术室，一直坐到十点多，医生出来跟我们说，还没脱离生命危险。", "text_postprocessed": "二 月 五 日 下 午 在 南 宁 市 大 学 东 路 西 往 东 方 向 一 辆 白 色 宝 马 轿 车 因 司 机 操 作 不 当 冲 撞 公 交 站 台 导 致 两 名 候 车 老 人 受 伤 三 月 二 日 记 者 了 解 到 其 中 一 名 七 十 七 岁 的 伤 者 经 抢 救 无 效 已 经 不 幸 离 世 事 故 发 生 在 当 天 上 午 十 点 四 十 一 分 左 右 肇 事 车 辆 冲 撞 南 宁 市 大 学 科 园 路 口 公 交 站 台 导 致 两 名 老 人 受 伤 送 医 受 害 者 家 属 罗 先 生 老 人 的 两 个 脚 都 是 骨 头 外 露 当 天 下 午 三 点 钟 进 了 手 术 室 一 直 坐 到 十 点 多 医 生 出 来 跟 我 们 说 还 没 脱 离 生 命 危 险", "time_stamp": [[110, 230], [230, 470], [470, 590], [590, 790], [790, 950], [950, 1190], [1370, 1610], [1610, 1710], [1710, 1890], [1890, 2090], [2090, 2190], [2190, 2390], [2390, 2550], [2550, 2750], [2750, 2910], [2910, 3030], [3030, 3230], [3230, 3330], [3330, 3570], [3870, 4050], [4050, 4250], [4250, 4350], [4350, 4590], [4610, 4710], [4710, 4910], [4910, 5070], [5070, 5310], [5310, 5530], [5530, 5670], [5670, 5870], [5870, 5970], [5970, 6150], [6150, 6270], [6270, 6510], [6690, 6870], [6870, 7110], [7130, 7230], [7230, 7430], [7430, 7590], [7590, 7830], [7930, 8070], [8070, 8210], [8210, 8370], [8370, 8550], [8550, 8730], [8730, 8930], [8930, 9090], [9090, 9230], [9230, 9390], [9390, 9630], [9910, 10090], [10090, 10270], [10270, 10390], [10390, 10630], [10870, 11050], [11050, 11210], [11210, 11350], [11350, 11530], [11530, 11770], [11990, 12190], [12190, 12330], [12330, 12490], [12490, 12710], [12710, 12850], [12850, 13030], [13030, 13150], [13150, 13330], [13330, 13430], [13430, 13570], [13570, 13810], [13830, 14030], [14030, 14230], [14230, 14430], [14430, 14530], [14530, 14770], [14930, 15070], [15070, 15270], [15270, 15370], [15370, 15570], [15570, 15730], [15730, 15970], [16170, 16390], [16390, 16590], [16590, 16690], [16690, 16870], [16870, 17070], [17070, 17230], [17230, 17370], [17370, 17530], [17530, 17650], [17650, 17830], [17830, 18030], [18030, 18190], [18190, 18290], [18290, 18410], [18410, 18570], [18570, 18710], [18710, 18950], [19190, 19370], [19370, 19510], [19510, 19670], [19670, 19910], [19930, 20090], [20090, 20330], [20350, 20450], [20450, 20630], [20630, 20830], [20830, 20990], [20990, 21190], [21190, 21350], [21350, 21470], [21470, 21650], [21650, 21870], [21870, 22010], [22010, 22150], [22150, 22310], [22310, 22550], [22930, 23090], [23090, 23290], [23290, 23450], [23450, 23590], [23590, 23750], [23750, 23890], [23890, 24050], [24050, 24190], [24190, 24410], [24410, 24650], [24830, 25070], [25070, 25250], [25250, 25410], [25410, 25550], [25550, 25730], [25730, 25870], [25870, 26030], [26030, 26270], [26570, 26810], [26810, 26930], [26930, 27070], [27070, 27210], [27210, 27390], [27390, 27630], [27650, 27810], [27810, 28010], [28010, 28110], [28110, 28250], [28250, 28470], [28470, 28710], [28910, 29070], [29070, 29270], [29270, 29430], [29430, 29570], [29570, 29730], [29730, 29910], [29910, 30150], [30150, 30270], [30270, 30410], [30410, 30570], [30570, 30750], [30750, 30990], [31110, 31350], [31350, 31550], [31550, 31710], [31710, 31850], [31850, 32009], [32009, 32189], [32189, 32430], [32770, 32970], [32970, 33170], [33170, 33330], [33330, 33450], [33450, 33590], [33590, 33750], [33750, 33870], [33870, 34110], [34510, 34710], [34710, 34850], [34850, 35070], [35070, 35250], [35250, 35370], [35370, 35510], [35510, 35670], [35670, 36055]], "sentences": [{"text": "二月五日下午,", "start": 110, "end": 1190}, {"text": "在南宁市大学东路西往东方向,", "start": 1190, "end": 3570}, {"text": "一辆白色宝马轿车,", "start": 3570, "end": 5310}, {"text": "因司机操作不当冲撞公交站台,", "start": 5310, "end": 7830}, {"text": "导致两名候车老人受伤.", "start": 7830, "end": 9630}, {"text": "三月二日,", "start": 9630, "end": 10630}, {"text": "记者了解到,", "start": 10630, "end": 11770}, {"text": "其中一名七十七岁的伤者经抢救无效,", "start": 11770, "end": 14770}, {"text": "已经不幸离世.", "start": 14770, "end": 15970}, {"text": "事故发生在当天上午十点四十一分左右,", "start": 15970, "end": 18950}, {"text": "肇事车辆冲撞.", "start": 18950, "end": 20330}, {"text": "南宁市大学科园路口公交站台,", "start": 20330, "end": 22550}, {"text": "导致两名老人受伤.", "start": 22550, "end": 24190}, {"text": "送医受害者家属罗先生,", "start": 24190, "end": 26270}, {"text": "老人的两个脚都是骨头外露.", "start": 26270, "end": 28710}, {"text": "当天下午三点钟进了手术室,", "start": 28710, "end": 30990}, {"text": "一直坐到十点多,", "start": 30990, "end": 32430}, {"text": "医生出来跟我们说,", "start": 32430, "end": 34110}, {"text": "还没脱离生命危险.", "start": 34110, "end": 36055}]}, "ocr_result": [{"frame": 0, "result": [["我单位指派/聘请有关人员对2021年02月05日在南宁市"], ["西乡塘区大学东路大学科园路口公交站交通事故中的桂"], [""], ["号小型轿车进行了车辆行驶速度鉴定,鉴定结论是事故前桂"], ["号小型轿车通过选取参照的现场空间直线 A 和直线 B 的"], ["行驶车速约为75km/h。"], ["根据《道路交通事故处理案程序规定》第五十六条之规定,如果"], ["你对该结论有异议,可以在接到本告知三日内提出补充鉴定或者"], ["重新鉴定的申请。"], ["2月5日下午"], ["在南宁市大学东路西往东方向"], ["一辆白色宝马轿车因司机操作不当"]]}, {"frame": 15, "result": [["后续|南宁一宝马车冲上"], ["公交站台撞伤2人"]]}, {"frame": 180, "result": [["后续"], ["南宁一宝马车冲上"], ["塘区大学东路大学科园路口公交站交通事故中的桂"], ["型轿车进行了车辆行驶速度鉴定,鉴定结论是事故前桂"], ["速约为75km/h。"], ["结论有异议,可以在接到本告知三日内提出补充鉴定或者"], ["定的申请。"], ["冲撞公交站台导致两名侯车老人受伤"]]}, {"frame": 195, "result": []}, {"frame": 255, "result": [["3月2日记者了解到"], ["其中一名77岁的伤者经抢救无效"], ["已经不幸离世"]]}, {"frame": 270, "result": []}, {"frame": 420, "result": [["1.左股骨下段、左侧胫骨、左膝骨上段及下段、右侧胫骨上段、右膳骨上段及中段多发骨"], ["侧腹夫节及!"], ["低青"], ["目行性变:"], ["右侧股骨、双侧踝关节平片检查骨质未见异常,"], ["事故发生在当天上午10点41分左右"], ["肇事车辆冲撞南宁市大学科园"], ["路口公交站台导致2名老人受伤送医"]]}, {"frame": 435, "result": [["1,左股骨下段、左侧胫骨、左腓骨上段及下段、右侧胫骨上段、右腰骨上段及中段多发骨折,如上"], ["2.双侧髋关节及骶型"], ["关节退行性变:"]]}, {"frame": 630, "result": [["如上"], [".双侧髋关节及低髂关节退行性变:"], ["受害者家属罗先生:"], ["老人的两个脚都是骨头外露"], ["当天下午3点钟进了手术室"]]}, {"frame": 645, "result": [["桂BD"]]}], "fps": 25.0}