{"video_id": "douyin_7027885300571573518", "wav_result": {"time_stamp": [], "sentences": []}, "ocr_result": [{"frame": 0, "result": []}, {"frame": 15, "result": []}, {"frame": 30, "result": []}, {"frame": 45, "result": []}, {"frame": 60, "result": [["青蜂侠"]]}, {"frame": 75, "result": [["青蜂侠"]]}, {"frame": 90, "result": [["清键侠"], ["强台风"], ["一海贝思"], [""], [""], ["12日登陆日本"]]}, {"frame": 120, "result": [["“海贝思"]]}, {"frame": 135, "result": [[""]]}, {"frame": 150, "result": [["”"]]}, {"frame": 165, "result": []}, {"frame": 180, "result": []}, {"frame": 195, "result": [["此次台风的破坏力"], ["超乎想象"], [""], ["气象厅"], ["向东京等多地发布最高级别的大雨警报"]]}, {"frame": 210, "result": [["此次台风的破坏力"], ["”"], ["向东京等多地发布最高级别的大雨警报"]]}, {"frame": 225, "result": [["超乎想象"], ["*"], ["向东京等多地发布最高级别的大雨警报"]]}, {"frame": 240, "result": [["此次台风的破坏力"], ["向东京等多地发布最高级别的大雨警报"], ["超乎想象"], [""]]}, {"frame": 255, "result": [["此次台风的破坏力"]]}, {"frame": 270, "result": [["“超乎想象"]]}, {"frame": 330, "result": [["此次台风的破坏力"]]}, {"frame": 345, "result": [["青蜂侠"], ["此次台风的破坏力"], ["“超乎想象"], [""]]}, {"frame": 405, "result": []}, {"frame": 435, "result": [["据自殊报道自即品"], ["目前合风已造成"], ["40人死世16人失踪"], ["180多人受伤"]]}, {"frame": 480, "result": [["据白踩报道目前白K"], ["40人死亡"], ["16大失踪180多人受伤"]]}, {"frame": 495, "result": [["40人死亡16人失踪180多人受份"], ["据口殊报導自型层一装"]]}, {"frame": 525, "result": [["青蜂侠"], ["据有殊报道自"], ["目前一风已造成"], ["40人死亡16大夫踪"], ["T80多人受伤"]]}, {"frame": 540, "result": [["据日媒报道"], ["目前台风已造成"], ["40人死亡"], ["16人失踪"], ["180多人受伤"]]}, {"frame": 555, "result": [["据白妹报"], ["目前台风已造成"], ["40人死亡16人失踪"]]}, {"frame": 570, "result": [["目前台风已造成"], ["16人失踪"]]}, {"frame": 600, "result": [["目前台风已造成"], ["40人死亡"], ["16人失踪"], ["180多人受伤"]]}, {"frame": 645, "result": []}, {"frame": 720, "result": [["宝宝艺"], ["还造成日本数十万户断电"], ["多条河川泛滥成灾"]]}, {"frame": 750, "result": [["多条河川泛滥成灾"]]}, {"frame": 810, "result": [["多条河川泛滥成灾"]]}, {"frame": 840, "result": [["还造成日本数十万户断电"]]}, {"frame": 855, "result": [["多条河川泛滥成灾"]]}, {"frame": 870, "result": []}, {"frame": 885, "result": [["还造成日本数十万户断电"], ["多条河川泛滥成灾"]]}, {"frame": 900, "result": [["还造成日本数十万户断电"]]}, {"frame": 915, "result": [["还造成日本数十万户断电"], ["多条河川泛滥成灾"]]}, {"frame": 930, "result": []}, {"frame": 945, "result": [["青蜂侠心"]]}, {"frame": 1020, "result": [["日本交通服务几乎全面停摆"], ["各地避难所挤满疏散民众"], ["入"]]}, {"frame": 1035, "result": []}, {"frame": 1050, "result": [["日本交通服务几乎全面停摆"], ["各地避难所挤满疏散民众"]]}, {"frame": 1065, "result": [["日本交通服务几乎全面停摆"], ["各地避难所挤满疏散民众"]]}, {"frame": 1080, "result": []}, {"frame": 1095, "result": [["青蜂侠"]]}, {"frame": 1110, "result": []}, {"frame": 1125, "result": [["日本交通服务几乎全面停摆"], ["各地避难所挤满疏散民众"]]}, {"frame": 1140, "result": [["各地避难所挤满疏散民众"]]}, {"frame": 1155, "result": [[""]]}, {"frame": 1170, "result": [["金子衣科品店"], ["日本交通服务几乎全面停摆"]]}, {"frame": 1305, "result": [["100"], ["D?INR"], ["100"], ["円"], ["DPN"], ["円"], [""], ["云"], ["原定于14日举行的日本"], ["海上自卫队阅舰式也被迫中止"], ["￥1On"]]}, {"frame": 1335, "result": [["青蜂快"], ["原定于14日举行的日本"], ["海上自卫队阅舰式也被迫中止"]]}, {"frame": 1365, "result": []}, {"frame": 1380, "result": []}, {"frame": 1410, "result": [["青蜂快"]]}, {"frame": 1425, "result": [["到各地清理积水和加紧救援"]]}, {"frame": 1440, "result": [["青蜂侠"], ["到各地清理积水和加紧救援"], ["安倍晋三下令派更多消防车"]]}, {"frame": 1455, "result": []}, {"frame": 1470, "result": []}, {"frame": 1485, "result": []}, {"frame": 1500, "result": []}, {"frame": 1515, "result": []}, {"frame": 1575, "result": []}, {"frame": 1590, "result": []}, {"frame": 1605, "result": [["编辑:孙册"], ["校审:西"], ["来源:外媒综合"]]}, {"frame": 1620, "result": [["青蜂侠"], ["编辑:孙丹丹(见习)"], ["校审:西湖雨"]]}], "fps": 30.0}