{"video_id": "douyin_6792888144355167500", "wav_result": {"text": "呀，你。", "text_postprocessed": "呀 你", "time_stamp": [[2849, 3090], [3090, 3330]], "sentences": [{"text": "呀,", "start": 2849, "end": 3090}, {"text": "你.", "start": 3090, "end": 3330}]}, "ocr_result": [{"frame": 0, "result": [["武汉某小区疑似一女子"], ["往楼道和门把手吐口水"]]}, {"frame": 90, "result": [["假的"], ["真相是并"], ["只是在"], ["2月8日晚有监控"], ["拍到一女子形迹可疑"]]}, {"frame": 105, "result": [["真相是并未张嘴"], ["贝"], ["只是在张望"]]}, {"frame": 135, "result": [["似乎在向门把手吐口水"], ["居民发现后已报警"]]}, {"frame": 150, "result": [["似乎在向门把手吐口水"], ["居民发现后已报警"]]}, {"frame": 165, "result": [["似乎在向门把手吐口水"], ["居民发现后已报警"]]}, {"frame": 195, "result": []}, {"frame": 210, "result": [["辟谣"], ["该"]]}, {"frame": 240, "result": [["该女子是一名中学生,"], ["因为玩手机被"]]}, {"frame": 255, "result": [["因为玩手机被训斥独自出门,"]]}, {"frame": 270, "result": [["她东张西望的时"]]}, {"frame": 315, "result": [["她东张西望的时候,"], ["9"], ["被住户监控探头拍下。"], ["民警反复"]]}, {"frame": 345, "result": [["下o"], ["民警反复确认视频,"], ["女子是在张望,"], ["并没有吐口水。"]]}, {"frame": 375, "result": [["该女子和家人,"], ["以及安装视频的一家人"], ["钧"]]}, {"frame": 435, "result": [["民警反复确认视频,"], ["女子是在张望,"], ["并没有吐口水。"], ["该女子和家人,"], ["以及安装视频的一家人"], ["均未感染新冠肺炎。"]]}, {"frame": 450, "result": [["更多疫情资讯"], ["关注楚天都市报"]]}], "fps": 30.0}