{"video_id": "douyin_6977581008392555784", "wav_result": {"text": "这个已经没事了，发微信号公交车司机，然后引倒了就不舒服。记住你的样子，名字像鱼。记住水的拥抱。", "text_postprocessed": "这 个 已 经 没 事 了 发 微 信 号 公 交 车 司 机 然 后 引 倒 了 就 不 舒 服 记 住 你 的 样 子 名 字 像 鱼 记 住 水 的 拥 抱", "time_stamp": [[6440, 6520], [6520, 6660], [6660, 6760], [6760, 6900], [6900, 7000], [7000, 7180], [7180, 7420], [7540, 7720], [7720, 7880], [7880, 8000], [8000, 8240], [8420, 8540], [8540, 8720], [8720, 8900], [8900, 9060], [9060, 9280], [9280, 9420], [9420, 9540], [9540, 9660], [9660, 9820], [9820, 10060], [10180, 10320], [10320, 10500], [10500, 10660], [10660, 10900], [11670, 11910], [12090, 12330], [12510, 12750], [12910, 13150], [13310, 13550], [13730, 14085], [15290, 15430], [15430, 15670], [17630, 17870], [18090, 18330], [18490, 18730], [18910, 19150], [19270, 19510], [19790, 20030], [20170, 20410], [20550, 20875]], "sentences": [{"text": "这个已经没事了,", "start": 6440, "end": 7420}, {"text": "发微信号公交车司机,", "start": 7420, "end": 9280}, {"text": "然后引倒了就不舒服.", "start": 9280, "end": 10900}, {"text": "记住你的样子,", "start": 10900, "end": 14085}, {"text": "名字像鱼.", "start": 14085, "end": 18330}, {"text": "记住水的拥抱.", "start": 18330, "end": 20875}]}, "ocr_result": [{"frame": 0, "result": [["公交车司机突发疾病"], ["晕倒前停稳车救下20多人"], ["车上乘客不愿离开暖心援救"], ["6月20日"], ["湖北十堰"]]}, {"frame": 30, "result": []}, {"frame": 60, "result": []}, {"frame": 75, "result": [["公交车司机突发疾病"], ["晕倒前停稳车救下20多人"]]}, {"frame": 90, "result": []}, {"frame": 120, "result": []}, {"frame": 135, "result": [["晕倒前停稳车救下20多人"]]}, {"frame": 150, "result": []}, {"frame": 165, "result": []}, {"frame": 180, "result": []}, {"frame": 195, "result": [["师傅你没事吧"]]}, {"frame": 225, "result": []}, {"frame": 240, "result": [["喂你好"]]}, {"frame": 255, "result": [["有个公交车司机晕倒了"]]}, {"frame": 270, "result": [["有个公交车司机晕倒了"]]}, {"frame": 285, "result": [["有个公交车司机晕倒了"]]}, {"frame": 300, "result": [["公交车司机突发疾病"], ["晕倒前停稳车救下20多人"], ["有个公交车司机晕倒了"]]}, {"frame": 315, "result": [["身体不舒服"]]}, {"frame": 330, "result": []}, {"frame": 345, "result": [["公交车司机突发疾病"]]}, {"frame": 360, "result": [["经诊断"], ["司机为突发性过敏性休克"], ["经治疗目前已无大碍"]]}, {"frame": 375, "result": [["司机为突发性过敏性休克"]]}, {"frame": 390, "result": []}, {"frame": 405, "result": [["经诊断"]]}, {"frame": 420, "result": []}, {"frame": 435, "result": []}, {"frame": 450, "result": []}, {"frame": 480, "result": [["司机为突发性过敏性休克"]]}, {"frame": 540, "result": []}, {"frame": 555, "result": []}, {"frame": 570, "result": []}, {"frame": 585, "result": []}, {"frame": 600, "result": []}, {"frame": 615, "result": []}, {"frame": 630, "result": []}, {"frame": 645, "result": []}], "fps": 30.0}