{"video_id": "douyin_6903095981676465411", "wav_result": {"text": "啦啦啦嗯。", "text_postprocessed": "啦 啦 啦 嗯", "time_stamp": [[6400, 6580], [6580, 6780], [6780, 6990], [8590, 8830]], "sentences": [{"text": "啦啦啦嗯.", "start": 6400, "end": 8830}]}, "ocr_result": [{"frame": 0, "result": [["教育局辟谣"], ["家长送老师不作为锦旗"], ["楚天交通广播"], [""], ["叫教"], ["常"], ["如果我"], ["纯属虚构"], ["做的话"], ["已申请警方介人"]]}, {"frame": 15, "result": [["系"], [""]]}, {"frame": 30, "result": [["楚天交通广播"], ["#"], ["叭格"], ["江苏徐州"]]}, {"frame": 45, "result": [["教育局辟谣"], ["插"], [""], ["夏"], ["噜"], ["12月6日"], ["还要"], ["纯属虚构"], ["么"]]}, {"frame": 60, "result": [["交通广播"], ["叫教"], ["蓝"], ["家嗆"], ["长"], ["么"]]}, {"frame": 75, "result": [["教育局辟谣"], ["家长送老师不作为锦旗"], ["老师送特制锦旗而走红》视频在微信"], ["群、QQ群等渠道传播,该视频主要"], ["内容为一名男子手持“教啥啥不行,"], ["叫家长第一名”的锦旗,反映徐州市"], ["天翔小学三(2)班赵西海老师频繁"], ["FM92.7"], ["叫家长去学校。"], ["徐州市教育局高度重视,迅速对"], ["该视频反映的内容进行核查。经排"], ["查,徐州市范围内无天翔小学,也无"], ["赵西海老师,该视频内容纯属虚构,"], ["造谣传谣,给徐州家校"], ["影响。徐州市教育局将依法依规进行"], ["处置。"], ["纯属虚构"], ["市教育局"], ["已申请警方乔人"]]}, {"frame": 90, "result": [["家长送老师不作为锦旗"], ["老师送特制锦旗而走红》视频在微信"], ["FM92.7"], ["徐州市教育局高度重视巾讯速对"], ["查,徐州市范围内无天翔小学,也无"], ["12月6日江苏徐州"]]}, {"frame": 105, "result": [["家长送老师不作为锦旗"], ["锦旗而走红》视频在微信"], ["营"], ["群等渠道传播,该视频主要"], ["内容为一名男子手持“教啥啥不行,"], [":"], ["该视频反映徐州市"], ["市"], ["天翔小学三西(2)师"], ["师频繁"], ["92.7"], ["班赵西海老师频繁"], ["对"], ["该"], ["叫家长去学校"], ["查。经排"], ["香"], ["徐州市节国内干干翔小学"], ["也无"], ["赵西海老师,该视频内容纯属虚构"], ["已申请警方介入"]]}, {"frame": 120, "result": [["教育局辟谣"], ["M92.7"], ["楚天交通广播"], [";"], ["徐州市范国内天天翔小学"], ["也无"], ["—徐州市教育局"]]}, {"frame": 225, "result": [["必"], ["笑"], ["市"], ["叫"], ["天翔小学二西屋师频繁"], ["译"], ["造谣传谣,给徐州家校共育造成不良"], ["纯属虚构"]]}, {"frame": 240, "result": []}, {"frame": 255, "result": [["持用"], ["内容为一名男子手持“教啥啥不行,"], ["."], ["经排查,的徐州市范"], ["市"], ["围内无天翔小学"], ["2"], ["叫家"], ["也无赵西海老师,"], ["速对"], ["该视频内容纯属虚"], ["排"], ["构,"], ["造谣传谣。"], ["小学,也无"], ["o"], ["老师"], ["该视频内容纯"], ["属虚构,"]]}], "fps": 30.0}