{"video_id": "douyin_7002792013359811870", "wav_result": {"text": "你晓得是不是他们撤掉哦？", "text_postprocessed": "你 晓 得 是 不 是 他 们 撤 掉 哦", "time_stamp": [[210, 350], [350, 450], [450, 550], [550, 730], [730, 810], [810, 890], [890, 970], [970, 1070], [1070, 1290], [1290, 1470], [1470, 1855]], "sentences": [{"text": "你晓得是不是他们撤掉哦?", "start": 210, "end": 1855}]}, "ocr_result": [{"frame": 0, "result": [["看度"], ["视频"], ["重庆4人自驾游失联疑坠入金沙江"], ["旅游中途曾与亲友进行过视频通话!"], ["近日"], ["不知道是不是他们的车哦"]]}, {"frame": 60, "result": [["重庆小"]]}, {"frame": 135, "result": [["视频"], ["重庆小伙带着母亲女友和堂弟到云南旅游"], ["8月24日失联至今"], ["其堂哥称24日前还一直保持联系"]]}, {"frame": 210, "result": [["旅游中途曾与亲友进行过视频通话!"]]}, {"frame": 225, "result": [["视频"], ["目前搜救工作仍在进行中"], ["警方怀疑车辆于2"]]}, {"frame": 300, "result": [["警方怀疑车辆于24日凌晨在途经四川甘孜州得荣县时"], ["坠崖冲入金沙江中目前搜救工作还在进行"], ["车辆和人员暂未找到"]]}, {"frame": 315, "result": [["目前搜救工作仍在进行中"], ["FOTO"], ["29"], ["V0653"], ["警方怀疑车辆于24日凌晨在途经四川甘孜州得荣县时"]]}, {"frame": 405, "result": [["看度"], ["十"]]}], "fps": 29.4}