{"video_id": "douyin_6791839171230174475", "wav_result": {"time_stamp": [], "sentences": []}, "ocr_result": [{"frame": 0, "result": [["女子朝电梯按键猛吐口水"], ["把用过的纸巾塞回原处"], ["重庆"], ["众志成城"], ["抗击疫情"]]}, {"frame": 15, "result": []}, {"frame": 30, "result": []}, {"frame": 45, "result": [["重庆"]]}, {"frame": 60, "result": []}, {"frame": 120, "result": []}, {"frame": 150, "result": []}, {"frame": 165, "result": []}, {"frame": 180, "result": []}, {"frame": 210, "result": []}, {"frame": 270, "result": []}, {"frame": 285, "result": []}, {"frame": 330, "result": []}, {"frame": 405, "result": []}, {"frame": 420, "result": [["李某(女"], ["48岁)"], ["目前已被警方刑事拘留"], ["警情通报"], ["网传一女子故意向电梯按键吐口水监控"], ["视频,警方迅速展开调查,在江北一小区将"], ["行为人李某(女,48岁)查获。据李某交代,"], ["因与他人发生纠纷心生怨恨,遂于2月9日9时"], ["许乘坐小区电梯时向按键吐口水发泄不满。"], ["经查,李某14天内无外地居住史,未接触湖"], ["北地区人员,体温正常。目前,李某已被警"], ["方刑事拘留。"]]}], "fps": 30.0}