{"video_id": "douyin_6915542827426467086", "wav_result": {"text": "我在这地方租了一个商铺呃，签的合同是三年使用期限是到二零二二年呃的六月份终止。但是由于商场把我的商铺又给另外一家签订了合同。就是这一个咱家乐准棒中泰店。然后呢，他让我搬走。丁先生说，物业之前也出面跟他做过沟通，让他自行离场。但是丁先生觉得自己在店铺倾注了不少心血，还有高额的装修费用，这样离场将承受较大的损失。因为我搬走呢，我的装修各方各方面的损失达到二十多万，我要求索赔，但是商场不给我索赔，然后找我协商，只愿意赔偿我两万块钱的损失，这肯定是达不到我的损失的，然后我就没同意，我就要求继续承租这个房子，继续履行合同，继续使用继续营业，就在双方协商未果的情况下，让丁先生意想不到的事情发生了，然后在商场在不在，我不知情的情况下，然后下午下商协商未果的情况下，然后把我的店把我的锁给我给我锯断了，把我的门也给我砸了，把我的所有的装修全部给我损坏了啊，然后又把把我的东西全部拉走了。然后我的店员也没地方上班，我也无法输入，也无法营业。我现在要求就是给我一个公道的说吧，他到底是属于倒销啊的东西，店铺为何被砸？为此记者找到了负责丁先生商铺片区的工作人员。呃，现在是这样的。呃，第一块呢就是说我们涉及目前的话，就是涉及到呃商铺的这个调整呢，总共是四家。然后呢，其中其他家三家呢，我们都是和平的，就是让呃解决掉了。其实我们甲方一直本着这个呃和平相处的这个这种态度，拿出一些诚意。所以说其他三家呢我们都顺利的就是说已经已经签署了这个相应的解除合同以及正式的这个呃租赁合同。就是比如说普惠的调整啊等等之类的啊，这是其他这是总共涉及到四家那三家的情况。针对呃一德安照相馆丁东这一块呢，就是说那我们呃作为甲方这一块呢，我们的初衷还是想本着这个和平共处以及这个公平公正的这种这这这种态度。然后我们想处理这个事情，然后在于前期呢我们呃也和呃照相馆丁东这边做一个沟通，我们想给他调整一些呃调整个位置，我们们还并不想叫他离开。我们就是说这个场地工作人员告知记者，在双方当初签订的租赁合同上有这样一条规定，即甲方如果以特殊原因提出解除合同需要赔付乙方两个月的房屋租金，现在这笔钱，他们愿意赔付，也愿意赔偿丁先生的装修损失费，但是损失费的金额，双方始终达不成一致。首先我们口头的协商了，下了过之后呢，我们又以纸质版的一一个一个一个告知啊，就是说呃目前的话存在的这个差距差距差距点在哪里呢？就是说呃他这一块的话，当时我们第一次然后交沟通交涉的呃沟通的时候呢，他是呃丁总这一块呢报价是十五万的赔偿啊，然后我们给他由于根据我们甲方的这个这个这个测算。然后的话呢跟我们这个赔偿的这个差距性比较大，然后呢我们就进行第二轮交涉，第二轮交涉呢，丁总这一块呢报价是二十万赔偿。然后那跟我们的差距，那我们们又又又又增大了一点差距。然后第三次我们交涉，然后下了第三次喊丁总这一块报价是二十七万啊。那么跟我们那个甲方，我们是这一块呃，完全不能接受这一块啊，对于他的被砸这一事实，工作人员承认，确实是他们所为丁先生的所有器材。目前他们已经妥善保管，截止涉及到一个赔偿赔偿问题，赔偿问题。他他这一块一直的给我们这个价呃差距比较大，一次是甚至约谈价格越高。我们这样的话对由于时间比较紧，所以说对于外观和损坏呢，这一块呢就是说嗯前期呢我们跟照相管的这块只能呃也在一起沟通，包括他的这个物品呢，这一块呢我们是他这一的就是说呃完好无缝的，然后这一块是给他打包好完好无风的，然后存放在一个合适的一个地方，对现是给他保管的保管好了。截止发稿时，记者了解到，双方仍未就此事达成一致意见，抖音。", "text_postprocessed": "我 在 这 地 方 租 了 一 个 商 铺 呃 签 的 合 同 是 三 年 使 用 期 限 是 到 二 零 二 二 年 呃 的 六 月 份 终 止 但 是 由 于 商 场 把 我 的 商 铺 又 给 另 外 一 家 签 订 了 合 同 就 是 这 一 个 咱 家 乐 准 棒 中 泰 店 然 后 呢 他 让 我 搬 走 丁 先 生 说 物 业 之 前 也 出 面 跟 他 做 过 沟 通 让 他 自 行 离 场 但 是 丁 先 生 觉 得 自 己 在 店 铺 倾 注 了 不 少 心 血 还 有 高 额 的 装 修 费 用 这 样 离 场 将 承 受 较 大 的 损 失 因 为 我 搬 走 呢 我 的 装 修 各 方 各 方 面 的 损 失 达 到 二 十 多 万 我 要 求 索 赔 但 是 商 场 不 给 我 索 赔 然 后 找 我 协 商 只 愿 意 赔 偿 我 两 万 块 钱 的 损 失 这 肯 定 是 达 不 到 我 的 损 失 的 然 后 我 就 没 同 意 我 就 要 求 继 续 承 租 这 个 房 子 继 续 履 行 合 同 继 续 使 用 继 续 营 业 就 在 双 方 协 商 未 果 的 情 况 下 让 丁 先 生 意 想 不 到 的 事 情 发 生 了 然 后 在 商 场 在 不 在 我 不 知 情 的 情 况 下 然 后 下 午 下 商 协 商 未 果 的 情 况 下 然 后 把 我 的 店 把 我 的 锁 给 我 给 我 锯 断 了 把 我 的 门 也 给 我 砸 了 把 我 的 所 有 的 装 修 全 部 给 我 损 坏 了 啊 然 后 又 把 把 我 的 东 西 全 部 拉 走 了 然 后 我 的 店 员 也 没 地 方 上 班 我 也 无 法 输 入 也 无 法 营 业 我 现 在 要 求 就 是 给 我 一 个 公 道 的 说 吧 他 到 底 是 属 于 倒 销 啊 的 东 西 店 铺 为 何 被 砸 为 此 记 者 找 到 了 负 责 丁 先 生 商 铺 片 区 的 工 作 人 员 呃 现 在 是 这 样 的 呃 第 一 块 呢 就 是 说 我 们 涉 及 目 前 的 话 就 是 涉 及 到 呃 商 铺 的 这 个 调 整 呢 总 共 是 四 家 然 后 呢 其 中 其 他 家 三 家 呢 我 们 都 是 和 平 的 就 是 让 呃 解 决 掉 了 其 实 我 们 甲 方 一 直 本 着 这 个 呃 和 平 相 处 的 这 个 这 种 态 度 拿 出 一 些 诚 意 所 以 说 其 他 三 家 呢 我 们 都 顺 利 的 就 是 说 已 经 已 经 签 署 了 这 个 相 应 的 解 除 合 同 以 及 正 式 的 这 个 呃 租 赁 合 同 就 是 比 如 说 普 惠 的 调 整 啊 等 等 之 类 的 啊 这 是 其 他 这 是 总 共 涉 及 到 四 家 那 三 家 的 情 况 针 对 呃 一 德 安 照 相 馆 丁 东 这 一 块 呢 就 是 说 那 我 们 呃 作 为 甲 方 这 一 块 呢 我 们 的 初 衷 还 是 想 本 着 这 个 和 平 共 处 以 及 这 个 公 平 公 正 的 这 种 这 这 这 种 态 度 然 后 我 们 想 处 理 这 个 事 情 然 后 在 于 前 期 呢 我 们 呃 也 和 呃 照 相 馆 丁 东 这 边 做 一 个 沟 通 我 们 想 给 他 调 整 一 些 呃 调 整 个 位 置 我 们 们 还 并 不 想 叫 他 离 开 我 们 就 是 说 这 个 场 地 工 作 人 员 告 知 记 者 在 双 方 当 初 签 订 的 租 赁 合 同 上 有 这 样 一 条 规 定 即 甲 方 如 果 以 特 殊 原 因 提 出 解 除 合 同 需 要 赔 付 乙 方 两 个 月 的 房 屋 租 金 现 在 这 笔 钱 他 们 愿 意 赔 付 也 愿 意 赔 偿 丁 先 生 的 装 修 损 失 费 但 是 损 失 费 的 金 额 双 方 始 终 达 不 成 一 致 首 先 我 们 口 头 的 协 商 了 下 了 过 之 后 呢 我 们 又 以 纸 质 版 的 一 一 个 一 个 一 个 告 知 啊 就 是 说 呃 目 前 的 话 存 在 的 这 个 差 距 差 距 差 距 点 在 哪 里 呢 就 是 说 呃 他 这 一 块 的 话 当 时 我 们 第 一 次 然 后 交 沟 通 交 涉 的 呃 沟 通 的 时 候 呢 他 是 呃 丁 总 这 一 块 呢 报 价 是 十 五 万 的 赔 偿 啊 然 后 我 们 给 他 由 于 根 据 我 们 甲 方 的 这 个 这 个 这 个 测 算 然 后 的 话 呢 跟 我 们 这 个 赔 偿 的 这 个 差 距 性 比 较 大 然 后 呢 我 们 就 进 行 第 二 轮 交 涉 第 二 轮 交 涉 呢 丁 总 这 一 块 呢 报 价 是 二 十 万 赔 偿 然 后 那 跟 我 们 的 差 距 那 我 们 们 又 又 又 又 增 大 了 一 点 差 距 然 后 第 三 次 我 们 交 涉 然 后 下 了 第 三 次 喊 丁 总 这 一 块 报 价 是 二 十 七 万 啊 那 么 跟 我 们 那 个 甲 方 我 们 是 这 一 块 呃 完 全 不 能 接 受 这 一 块 啊 对 于 他 的 被 砸 这 一 事 实 工 作 人 员 承 认 确 实 是 他 们 所 为 丁 先 生 的 所 有 器 材 目 前 他 们 已 经 妥 善 保 管 截 止 涉 及 到 一 个 赔 偿 赔 偿 问 题 赔 偿 问 题 他 他 这 一 块 一 直 的 给 我 们 这 个 价 呃 差 距 比 较 大 一 次 是 甚 至 约 谈 价 格 越 高 我 们 这 样 的 话 对 由 于 时 间 比 较 紧 所 以 说 对 于 外 观 和 损 坏 呢 这 一 块 呢 就 是 说 嗯 前 期 呢 我 们 跟 照 相 管 的 这 块 只 能 呃 也 在 一 起 沟 通 包 括 他 的 这 个 物 品 呢 这 一 块 呢 我 们 是 他 这 一 的 就 是 说 呃 完 好 无 缝 的 然 后 这 一 块 是 给 他 打 包 好 完 好 无 风 的 然 后 存 放 在 一 个 合 适 的 一 个 地 方 对 现 是 给 他 保 管 的 保 管 好 了 截 止 发 稿 时 记 者 了 解 到 双 方 仍 未 就 此 事 达 成 一 致 意 见 抖 音", "time_stamp": [[290, 390], [390, 510], [510, 630], [630, 710], [710, 810], [810, 890], [890, 990], [990, 1070], [1070, 1170], [1170, 1290], [1290, 1530], [1890, 2130], [2350, 2550], [2550, 2630], [2630, 2730], [2730, 2810], [2810, 2910], [2910, 3010], [3010, 3210], [3210, 3310], [3310, 3430], [3430, 3550], [3550, 3670], [3670, 3790], [3790, 3930], [3930, 4030], [4030, 4270], [4290, 4390], [4390, 4570], [4570, 4810], [5170, 5350], [5350, 5550], [5550, 5650], [5650, 5770], [5770, 5890], [5890, 5990], [5990, 6230], [6710, 6890], [6890, 7010], [7010, 7130], [7130, 7230], [7230, 7310], [7310, 7530], [7530, 7690], [7690, 7790], [7790, 8029], [8350, 8590], [8630, 8870], [9210, 9350], [9350, 9550], [9550, 9650], [9650, 9770], [9770, 9850], [9850, 9950], [9950, 10050], [10050, 10170], [10170, 10270], [10270, 10350], [10350, 10530], [10530, 10650], [10650, 10770], [10770, 10890], [10890, 11010], [11010, 11250], [11470, 11610], [11610, 11730], [11730, 11870], [11870, 11970], [11970, 12210], [12330, 12450], [12450, 12630], [12630, 12895], [13620, 13760], [13760, 13860], [13860, 13980], [13980, 14080], [14080, 14160], [14160, 14280], [14280, 14400], [14400, 14640], [15100, 15299], [15299, 15420], [15420, 15540], [15540, 15780], [15860, 15959], [15959, 16160], [16160, 16259], [16259, 16500], [16500, 16700], [16700, 16860], [16860, 17040], [17040, 17140], [17140, 17300], [17300, 17439], [17439, 17580], [17580, 17680], [17680, 17920], [17960, 18100], [18100, 18240], [18240, 18340], [18340, 18540], [18540, 18640], [18640, 18880], [19100, 19240], [19240, 19360], [19360, 19480], [19480, 19660], [19660, 19780], [19780, 19880], [19880, 20080], [20080, 20240], [20240, 20420], [20420, 20660], [20680, 20840], [20840, 21060], [21060, 21200], [21200, 21380], [21380, 21460], [21460, 21560], [21560, 21759], [21759, 21920], [21920, 22160], [22200, 22340], [22340, 22460], [22460, 22580], [22580, 22740], [22740, 22840], [22840, 22939], [22939, 23119], [23119, 23280], [23280, 23520], [23660, 23820], [23820, 23939], [23939, 24060], [24060, 24300], [24320, 24520], [24520, 24720], [24720, 24960], [25000, 25200], [25200, 25320], [25320, 25460], [25460, 25560], [25560, 25855], [26470, 26630], [26630, 26710], [26710, 26810], [26810, 26910], [26910, 27030], [27030, 27270], [27310, 27410], [27410, 27550], [27550, 27750], [27750, 27990], [28470, 28630], [28630, 28830], [28830, 28910], [28910, 29009], [29009, 29090], [29090, 29190], [29190, 29270], [29270, 29370], [29370, 29450], [29450, 29550], [29550, 29630], [29630, 29730], [29730, 29810], [29810, 30050], [30310, 30470], [30470, 30570], [30570, 30710], [30710, 30870], [30870, 31110], [31470, 31650], [31650, 31750], [31750, 31830], [31830, 32009], [32009, 32130], [32130, 32210], [32210, 32350], [32350, 32490], [32490, 32730], [33010, 33150], [33150, 33269], [33269, 33350], [33350, 33470], [33470, 33630], [33630, 33870], [34130, 34250], [34250, 34390], [34390, 34490], [34490, 34570], [34570, 34670], [34670, 34769], [34769, 34870], [34870, 35030], [35030, 35170], [35170, 35290], [35290, 35390], [35390, 35530], [35530, 35769], [35910, 36090], [36090, 36190], [36190, 36269], [36269, 36350], [36350, 36450], [36450, 36530], [36530, 36610], [36610, 36710], [36710, 36810], [36810, 36890], [36890, 37070], [37070, 37310], [37530, 37670], [37670, 37769], [37769, 37850], [37850, 37930], [37930, 38050], [38050, 38150], [38150, 38390], [38390, 38510], [38510, 38650], [38650, 38750], [38750, 38990], [39110, 39290], [39290, 39530], [39810, 40010], [40010, 40170], [40170, 40269], [40269, 40350], [40350, 40470], [40470, 40710], [40810, 41010], [41010, 41210], [41210, 41310], [41310, 41470], [41470, 41610], [41610, 41810], [41810, 41910], [41910, 42030], [42030, 42150], [42150, 42290], [42290, 42390], [42390, 42530], [42530, 42629], [42629, 42894], [43820, 43960], [43960, 44100], [44100, 44260], [44260, 44480], [44480, 44680], [44680, 44820], [44820, 44960], [44960, 45080], [45080, 45220], [45220, 45320], [45320, 45500], [45500, 45680], [45680, 45860], [45860, 46040], [46040, 46199], [46199, 46440], [46460, 46620], [46620, 46860], [46860, 47040], [47040, 47140], [47140, 47280], [47280, 47379], [47379, 47620], [47660, 47800], [47800, 47980], [47980, 48245], [48950, 49089], [49089, 49170], [49170, 49270], [49270, 49370], [49370, 49589], [49589, 49730], [49730, 49970], [50150, 50270], [50270, 50390], [50390, 50530], [50530, 50630], [50630, 50750], [50750, 50850], [50850, 50930], [50930, 51050], [51050, 51290], [51550, 51710], [51710, 51830], [51830, 51950], [51950, 52130], [52130, 52290], [52290, 52490], [52490, 52590], [52590, 52730], [52730, 52890], [52890, 52990], [52990, 53070], [53070, 53150], [53150, 53250], [53250, 53490], [53630, 53790], [53790, 53910], [53910, 54030], [54030, 54150], [54150, 54230], [54230, 54470], [54590, 54750], [54750, 54830], [54830, 54930], [54930, 55110], [55110, 55190], [55190, 55410], [55410, 55490], [55490, 55570], [55570, 55650], [55650, 55810], [55810, 56050], [56210, 56350], [56350, 56470], [56470, 56550], [56550, 56710], [56710, 56850], [56850, 56930], [56930, 57010], [57010, 57090], [57090, 57330], [57550, 57710], [57710, 57830], [57830, 58030], [58030, 58130], [58130, 58250], [58250, 58350], [58350, 58490], [58490, 58670], [58670, 58790], [58790, 58910], [58910, 58990], [58990, 59090], [59090, 59210], [59210, 59330], [59330, 59570], [59730, 59970], [60010, 60230], [60230, 60470], [61090, 61310], [61310, 61635], [62440, 62600], [62600, 62680], [62680, 62780], [62780, 62860], [62860, 62960], [62960, 63080], [63080, 63199], [63199, 63320], [63320, 63559], [63879, 64039], [64039, 64160], [64160, 64239], [64239, 64319], [64319, 64459], [64459, 64599], [64599, 64700], [64700, 64819], [64819, 64900], [64900, 65019], [65019, 65179], [65179, 65420], [65480, 65600], [65600, 65720], [65720, 65840], [65840, 65960], [65960, 66060], [66060, 66160], [66160, 66340], [66340, 66480], [66480, 66580], [66580, 66720], [66720, 66880], [66880, 67120], [67320, 67480], [67480, 67580], [67580, 67679], [67679, 67760], [67760, 68000], [68280, 68420], [68420, 68539], [68539, 68620], [68620, 68720], [68720, 68800], [68800, 68880], [68880, 68960], [68960, 69039], [69039, 69140], [69140, 69320], [69320, 69440], [69440, 69560], [69560, 69679], [69679, 69760], [69760, 69840], [69840, 69940], [69940, 70020], [70020, 70179], [70179, 70320], [70320, 70420], [70420, 70539], [70539, 70660], [70660, 70900], [71100, 71300], [71300, 71440], [71440, 71600], [71600, 71740], [71740, 71900], [71900, 72140], [72200, 72380], [72380, 72580], [72580, 72679], [72679, 72800], [72800, 72920], [72920, 73039], [73039, 73179], [73179, 73340], [73340, 73520], [73520, 73720], [73720, 73880], [73880, 74080], [74080, 74240], [74240, 74460], [74460, 74600], [74600, 74780], [74780, 74900], [74900, 75020], [75020, 75180], [75180, 75320], [75320, 75560], [75980, 76180], [76180, 76340], [76340, 76460], [76460, 76600], [76600, 76700], [76700, 76820], [76820, 77060], [77300, 77539], [77560, 77720], [77720, 77840], [77840, 77960], [77960, 78140], [78140, 78220], [78220, 78320], [78320, 78460], [78460, 78560], [78560, 78800], [78840, 79039], [79039, 79240], [79240, 79400], [79400, 79580], [79580, 79660], [79660, 79820], [79820, 79940], [79940, 80080], [80080, 80180], [80180, 80300], [80300, 80539], [80800, 81039], [81180, 81380], [81380, 81560], [81560, 81640], [81640, 81740], [81740, 81880], [81880, 81980], [81980, 82160], [82160, 82360], [82360, 82460], [82460, 82640], [82640, 82800], [82800, 83000], [83000, 83240], [83560, 83720], [83720, 83880], [83880, 84120], [84420, 84660], [84660, 84880], [84880, 85020], [85020, 85200], [85200, 85380], [85380, 85500], [85500, 85680], [85680, 85860], [85860, 85960], [85960, 86100], [86100, 86220], [86220, 86460], [86500, 86640], [86640, 86759], [86759, 86880], [86880, 87000], [87000, 87140], [87140, 87380], [87380, 87620], [87759, 87900], [87900, 88020], [88020, 88140], [88140, 88380], [88440, 88560], [88560, 88660], [88660, 88740], [88740, 88820], [88820, 88920], [88920, 89120], [89120, 89220], [89220, 89360], [89360, 89520], [89520, 89640], [89640, 89820], [89820, 90060], [90220, 90460], [90460, 90660], [90660, 90900], [91140, 91320], [91320, 91440], [91440, 91560], [91560, 91680], [91680, 91920], [92020, 92100], [92100, 92259], [92259, 92380], [92380, 92560], [92560, 92680], [92680, 92820], [92820, 92920], [92920, 93100], [93100, 93220], [93220, 93460], [93700, 93820], [93820, 93940], [93940, 94080], [94080, 94180], [94180, 94300], [94300, 94420], [94420, 94600], [94600, 94840], [94940, 95080], [95080, 95160], [95160, 95280], [95280, 95440], [95440, 95600], [95600, 95740], [95740, 95840], [95840, 95940], [95940, 96120], [96120, 96220], [96220, 96400], [96400, 96500], [96500, 96640], [96640, 96800], [96800, 96920], [96920, 97039], [97039, 97160], [97160, 97259], [97259, 97340], [97340, 97460], [97460, 97600], [97600, 97700], [97700, 97820], [97820, 97940], [97940, 98120], [98120, 98240], [98240, 98420], [98420, 98600], [98600, 98720], [98720, 98840], [98840, 98960], [98960, 99200], [99280, 99479], [99479, 99580], [99580, 99759], [99759, 99860], [99860, 99979], [99979, 100100], [100100, 100240], [100240, 100340], [100340, 100440], [100440, 100580], [100580, 100700], [100700, 100800], [100800, 100920], [100920, 101020], [101020, 101140], [101140, 101300], [101300, 101380], [101380, 101520], [101520, 101620], [101620, 101740], [101740, 101940], [101940, 102160], [102160, 102280], [102280, 102380], [102380, 102460], [102460, 102700], [102840, 103000], [103000, 103120], [103120, 103200], [103200, 103380], [103380, 103479], [103479, 103560], [103560, 103680], [103680, 103780], [103780, 103960], [103960, 104080], [104080, 104200], [104200, 104320], [104320, 104460], [104460, 104560], [104560, 104800], [105000, 105160], [105160, 105280], [105280, 105520], [105780, 105979], [105979, 106120], [106120, 106200], [106200, 106320], [106320, 106420], [106420, 106539], [106539, 106759], [106759, 106900], [106900, 107120], [107120, 107259], [107259, 107340], [107340, 107440], [107440, 107560], [107560, 107680], [107680, 107800], [107800, 108039], [108240, 108380], [108380, 108479], [108479, 108720], [108960, 109200], [109360, 109500], [109500, 109620], [109620, 109740], [109740, 109920], [109920, 110000], [110000, 110100], [110100, 110180], [110180, 110280], [110280, 110360], [110360, 110440], [110440, 110539], [110539, 110700], [110700, 110940], [110960, 111060], [111060, 111180], [111180, 111320], [111320, 111479], [111479, 111680], [111680, 111780], [111780, 111940], [111940, 112080], [112080, 112240], [112240, 112440], [112440, 112680], [113000, 113160], [113160, 113340], [113340, 113460], [113460, 113700], [113920, 114120], [114120, 114360], [114400, 114539], [114539, 114660], [114660, 114780], [114780, 114860], [114860, 115039], [115039, 115280], [115479, 115580], [115580, 115740], [115740, 115880], [115880, 116120], [116200, 116360], [116360, 116440], [116440, 116539], [116539, 116620], [116620, 116860], [116920, 117080], [117080, 117259], [117259, 117340], [117340, 117420], [117420, 117520], [117520, 117759], [117940, 118100], [118100, 118320], [118320, 118520], [118520, 118700], [118700, 118880], [118880, 118960], [118960, 119140], [119140, 119320], [119320, 119440], [119440, 119680], [119880, 120120], [120120, 120340], [120340, 120580], [121200, 121340], [121340, 121460], [121460, 121640], [121640, 121759], [121759, 121940], [121940, 122020], [122020, 122210], [122350, 122450], [122450, 122530], [122530, 122630], [122630, 122770], [122770, 122910], [122910, 122990], [122990, 123090], [123090, 123270], [123270, 123350], [123350, 123490], [123490, 123570], [123570, 123710], [123710, 123850], [123850, 124090], [124090, 124289], [124289, 124410], [124410, 124530], [124530, 124630], [124630, 124710], [124710, 124890], [124890, 125009], [125009, 125190], [125190, 125429], [125530, 125690], [125690, 125789], [125789, 126030], [126250, 126390], [126390, 126630], [126950, 127050], [127050, 127229], [127229, 127350], [127350, 127590], [127670, 127770], [127770, 127929], [127929, 128169], [128250, 128410], [128410, 128490], [128490, 128609], [128609, 128729], [128729, 128970], [129270, 129449], [129449, 129570], [129570, 129690], [129690, 129789], [129789, 129930], [129930, 130070], [130070, 130169], [130169, 130410], [130530, 130750], [130750, 130889], [130889, 131109], [131109, 131250], [131250, 131470], [131470, 131609], [131609, 131730], [131730, 131870], [131870, 131970], [131970, 132109], [132109, 132269], [132269, 132390], [132390, 132630], [132630, 132829], [132829, 132930], [132930, 133050], [133050, 133170], [133170, 133310], [133310, 133470], [133470, 133710], [133730, 133970], [134109, 134350], [134370, 134530], [134530, 134670], [134670, 134790], [134790, 134990], [134990, 135150], [135150, 135350], [135350, 135450], [135450, 135650], [135650, 135810], [135810, 136010], [136010, 136170], [136170, 136350], [136350, 136470], [136470, 136710], [136870, 137010], [137010, 137150], [137150, 137310], [137310, 137450], [137450, 137609], [137609, 137850], [137870, 138030], [138030, 138150], [138150, 138269], [138269, 138470], [138470, 138570], [138570, 138750], [138750, 138870], [138870, 139109], [139530, 139710], [139710, 139890], [139890, 140070], [140070, 140190], [140190, 140430], [140450, 140550], [140550, 140750], [140750, 140850], [140850, 140990], [140990, 141150], [141150, 141390], [141470, 141650], [141650, 141810], [141810, 141950], [141950, 142050], [142050, 142230], [142230, 142370], [142370, 142530], [142530, 142710], [142710, 142850], [142850, 142950], [142950, 143150], [143150, 143310], [143310, 143490], [143490, 143730], [143910, 144090], [144090, 144290], [144290, 144450], [144450, 144630], [144630, 144750], [144750, 144870], [144870, 144990], [144990, 145230], [145350, 145530], [145530, 145769], [145829, 146010], [146010, 146250], [146329, 146490], [146490, 146609], [146609, 146810], [146810, 146970], [146970, 147210], [147510, 147690], [147690, 147850], [147850, 147950], [147950, 148050], [148050, 148210], [148210, 148390], [148390, 148510], [148510, 148630], [148630, 148810], [148810, 149050], [149290, 149410], [149410, 149530], [149530, 149650], [149650, 149730], [149730, 149829], [149829, 149950], [149950, 150070], [150070, 150150], [150150, 150250], [150250, 150390], [150390, 150490], [150490, 150609], [150609, 150730], [150730, 150870], [150870, 151109], [151190, 151370], [151370, 151510], [151510, 151670], [151670, 151769], [151769, 151870], [151870, 152030], [152030, 152170], [152170, 152410], [152670, 152890], [152890, 153010], [153010, 153130], [153130, 153370], [153590, 153829], [153950, 154090], [154090, 154269], [154269, 154370], [154370, 154530], [154530, 154690], [154690, 154810], [154810, 154930], [154930, 155030], [155030, 155190], [155190, 155329], [155329, 155570], [155930, 156110], [156110, 156350], [156570, 156710], [156710, 156829], [156829, 156970], [156970, 157070], [157070, 157190], [157190, 157310], [157310, 157550], [157710, 157850], [157850, 157970], [157970, 158210], [158410, 158650], [158810, 158950], [158950, 159050], [159050, 159130], [159130, 159250], [159250, 159350], [159350, 159590], [159690, 159829], [159829, 160070], [160110, 160190], [160190, 160430], [160570, 160790], [160790, 160910], [160910, 161150], [161370, 161510], [161510, 161690], [161690, 161930], [162130, 162290], [162290, 162470], [162470, 162590], [162590, 162710], [162710, 162890], [162890, 163110], [163110, 163250], [163250, 163370], [163370, 163490], [163490, 163570], [163570, 163670], [163670, 163910], [163990, 164150], [164150, 164350], [164350, 164590], [164610, 164710], [164710, 164850], [164850, 164950], [164950, 165030], [165030, 165130], [165130, 165250], [165250, 165329], [165329, 165490], [165490, 165730], [166090, 166210], [166210, 166329], [166329, 166450], [166450, 166530], [166530, 166630], [166630, 166870], [167110, 167350], [167530, 167710], [167710, 167829], [167829, 167950], [167950, 168070], [168070, 168190], [168190, 168430], [168829, 168950], [168950, 169190], [169190, 169310], [169310, 169490], [169490, 169570], [169570, 169730], [169730, 169850], [169850, 169970], [169970, 170110], [170110, 170210], [170210, 170390], [170390, 170510], [170510, 170630], [170630, 170750], [170750, 170850], [170850, 170990], [170990, 171230], [171530, 171650], [171650, 171790], [171790, 171890], [171890, 171990], [171990, 172230], [172450, 172570], [172570, 172670], [172670, 172790], [172790, 172910], [172910, 172990], [172990, 173070], [173070, 173170], [173170, 173269], [173269, 173350], [173350, 173430], [173430, 173530], [173530, 173690], [173690, 173890], [173890, 173970], [173970, 174090], [174090, 174329], [174570, 174690], [174690, 174810], [174810, 174950], [174950, 175050], [175050, 175150], [175150, 175290], [175290, 175410], [175410, 175650], [175650, 175769], [175769, 175850], [175850, 175990], [175990, 176130], [176130, 176370], [176510, 176670], [176670, 176750], [176750, 176850], [176850, 176970], [176970, 177090], [177090, 177210], [177210, 177329], [177329, 177450], [177450, 177530], [177530, 177630], [177630, 177710], [177710, 177829], [177829, 177930], [177930, 178110], [178110, 178350], [178490, 178590], [178590, 178710], [178710, 178890], [178890, 179010], [179010, 179250], [179550, 179670], [179670, 179850], [179850, 180090], [180269, 180450], [180450, 180530], [180530, 180630], [180630, 180710], [180710, 180810], [180810, 180990], [180990, 181070], [181070, 181250], [181250, 181370], [181370, 181610], [181690, 181930], [182239, 182440], [182440, 182640], [182640, 182739], [182739, 182859], [182859, 182940], [182940, 183019], [183019, 183119], [183119, 183220], [183220, 183459], [183619, 183760], [183760, 183880], [183880, 183959], [183959, 184160], [184160, 184260], [184260, 184500], [184519, 184619], [184619, 184859], [185100, 185339], [185339, 185579], [185579, 185660], [185660, 185760], [185760, 185880], [185880, 185959], [185959, 186059], [186059, 186179], [186179, 186299], [186299, 186480], [186480, 186579], [186579, 186720], [186720, 186820], [186820, 186940], [186940, 187140], [187140, 187299], [187299, 187480], [187480, 187700], [187700, 187780], [187780, 187899], [187899, 188019], [188019, 188260], [188560, 188799], [188859, 189040], [189040, 189280], [189299, 189459], [189459, 189540], [189540, 189660], [189660, 189760], [189760, 189880], [189880, 190000], [190000, 190239], [190239, 190320], [190320, 190480], [190480, 190720], [190739, 190839], [190839, 190920], [190920, 191160], [191359, 191600], [191700, 191859], [191859, 192040], [192040, 192119], [192119, 192239], [192239, 192399], [192399, 192579], [192579, 192700], [192700, 192779], [192779, 192940], [192940, 193179], [193660, 193839], [193839, 194019], [194019, 194140], [194140, 194320], [194320, 194440], [194440, 194619], [194619, 194739], [194739, 194820], [194820, 194980], [194980, 195220], [195220, 195339], [195339, 195480], [195480, 195579], [195579, 195720], [195720, 195820], [195820, 196060], [196079, 196239], [196239, 196420], [196420, 196540], [196540, 196660], [196660, 196779], [196779, 196899], [196899, 197140], [197140, 197320], [197320, 197500], [197500, 197619], [197619, 197760], [197760, 197859], [197859, 198060], [198060, 198220], [198220, 198420], [198420, 198579], [198579, 198760], [198760, 198859], [198859, 199000], [199000, 199079], [199079, 199260], [199260, 199399], [199399, 199600], [199600, 199760], [199760, 200000], [200359, 200480], [200480, 200679], [200679, 200779], [200779, 200959], [200959, 201060], [201060, 201140], [201140, 201279], [201279, 201380], [201380, 201619], [201760, 201859], [201859, 201980], [201980, 202100], [202100, 202339], [202359, 202459], [202459, 202579], [202579, 202700], [202700, 202940], [202940, 203179], [203339, 203540], [203540, 203660], [203660, 203760], [203760, 204000], [204000, 204140], [204140, 204320], [204320, 204459], [204459, 204560], [204560, 204660], [204660, 204779], [204779, 204880], [204880, 205060], [205060, 205299], [205320, 205560], [205700, 205839], [205839, 205959], [205959, 206079], [206079, 206160], [206160, 206399], [206440, 206560], [206560, 206799], [206820, 207060], [207600, 207700], [207700, 207899], [207899, 208000], [208000, 208239], [208339, 208480], [208480, 208600], [208600, 208720], [208720, 208959], [209220, 209320], [209320, 209500], [209500, 209579], [209579, 209679], [209679, 209760], [209760, 209920], [209920, 210160], [210220, 210339], [210339, 210480], [210480, 210560], [210560, 210700], [210700, 210820], [210820, 210899], [210899, 211119], [211119, 211239], [211239, 211320], [211320, 211560], [212100, 212320], [212320, 212560], [212760, 212920], [212920, 213040], [213040, 213220], [213220, 213339], [213339, 213459], [213459, 213660], [213660, 213760], [213760, 213839], [213839, 213940], [213940, 214119], [214119, 214239], [214239, 214359], [214359, 214600], [214859, 215100], [215339, 215500], [215500, 215679], [215679, 215799], [215799, 215880], [215880, 216079], [216079, 216320], [216480, 216620], [216620, 216720], [216720, 216820], [216820, 216940], [216940, 217019], [217019, 217140], [217140, 217299], [217299, 217399], [217399, 217579], [217579, 217760], [217760, 217980], [217980, 218140], [218140, 218260], [218260, 218359], [218359, 218440], [218440, 218679], [218779, 218920], [218920, 219100], [219100, 219220], [219220, 219339], [219339, 219420], [219420, 219660], [219660, 219820], [219820, 220000], [220000, 220179], [220179, 220299], [220299, 220380], [220380, 220480], [220480, 220640], [220640, 220720], [220720, 220899], [220899, 221140], [221480, 221679], [221679, 221859], [221859, 222040], [222040, 222160], [222160, 222279], [222279, 222519], [222720, 222920], [222920, 223060], [223060, 223260], [223260, 223359], [223359, 223540], [223540, 223739], [223739, 223839], [223839, 223940], [223940, 224019], [224019, 224120], [224120, 224260], [224260, 224399], [224399, 224500], [224500, 224640], [224640, 224739], [224739, 224920], [224920, 225160], [225480, 225579], [225579, 225779], [225779, 225940], [225940, 226060], [226060, 226260], [226260, 226359], [226359, 226480], [226480, 226600], [226600, 226839], [226839, 227040], [227040, 227140], [227140, 227279], [227279, 227380], [227380, 227500], [227500, 227600], [227600, 227679], [227679, 227760], [227760, 227859], [227859, 228100], [228239, 228480], [228480, 228579], [228579, 228820], [229200, 229299], [229299, 229519], [229519, 229660], [229660, 229779], [229779, 229980], [229980, 230079], [230079, 230200], [230200, 230320], [230320, 230560], [231019, 231220], [231220, 231339], [231339, 231459], [231459, 231640], [231640, 231880], [231899, 232000], [232000, 232120], [232120, 232239], [232239, 232359], [232359, 232600], [232620, 232779], [232779, 233019], [233100, 233260], [233260, 233440], [233440, 233640], [233640, 233799], [233799, 234040], [234140, 234279], [234279, 234519], [234540, 234700], [234700, 234880], [234880, 234980], [234980, 235295], [236810, 237050], [237090, 237395]], "sentences": [{"text": "我在这地方租了一个商铺呃,", "start": 290, "end": 2130}, {"text": "签的合同是三年使用期限是到二零二二年呃的六月份终止.", "start": 2130, "end": 6230}, {"text": "但是由于商场把我的商铺又给另外一家签订了合同.", "start": 6230, "end": 10530}, {"text": "就是这一个咱家乐准棒中泰店.", "start": 10530, "end": 12895}, {"text": "然后呢,", "start": 12895, "end": 13980}, {"text": "他让我搬走.", "start": 13980, "end": 14640}, {"text": "丁先生说,", "start": 14640, "end": 15780}, {"text": "物业之前也出面跟他做过沟通,", "start": 15780, "end": 17920}, {"text": "让他自行离场.", "start": 17920, "end": 18880}, {"text": "但是丁先生觉得自己在店铺倾注了不少心血,", "start": 18880, "end": 22160}, {"text": "还有高额的装修费用,", "start": 22160, "end": 23520}, {"text": "这样离场将承受较大的损失.", "start": 23520, "end": 25855}, {"text": "因为我搬走呢,", "start": 25855, "end": 27270}, {"text": "我的装修各方各方面的损失达到二十多万,", "start": 27270, "end": 30050}, {"text": "我要求索赔,", "start": 30050, "end": 31110}, {"text": "但是商场不给我索赔,", "start": 31110, "end": 32730}, {"text": "然后找我协商,", "start": 32730, "end": 33870}, {"text": "只愿意赔偿我两万块钱的损失,", "start": 33870, "end": 35769}, {"text": "这肯定是达不到我的损失的,", "start": 35769, "end": 37310}, {"text": "然后我就没同意,", "start": 37310, "end": 38390}, {"text": "我就要求继续承租这个房子,", "start": 38390, "end": 40710}, {"text": "继续履行合同,", "start": 40710, "end": 41810}, {"text": "继续使用继续营业,", "start": 41810, "end": 42894}, {"text": "就在双方协商未果的情况下,", "start": 42894, "end": 45680}, {"text": "让丁先生意想不到的事情发生了,", "start": 45680, "end": 48245}, {"text": "然后在商场在不在,", "start": 48245, "end": 50270}, {"text": "我不知情的情况下,", "start": 50270, "end": 51290}, {"text": "然后下午下商协商未果的情况下,", "start": 51290, "end": 53490}, {"text": "然后把我的店把我的锁给我给我锯断了,", "start": 53490, "end": 56050}, {"text": "把我的门也给我砸了,", "start": 56050, "end": 57330}, {"text": "把我的所有的装修全部给我损坏了啊,", "start": 57330, "end": 59970}, {"text": "然后又把把我的东西全部拉走了.", "start": 59970, "end": 64039}, {"text": "然后我的店员也没地方上班,", "start": 64039, "end": 65600}, {"text": "我也无法输入,", "start": 65600, "end": 66340}, {"text": "也无法营业.", "start": 66340, "end": 67120}, {"text": "我现在要求就是给我一个公道的说吧,", "start": 67120, "end": 69440}, {"text": "他到底是属于倒销啊的东西,", "start": 69440, "end": 70900}, {"text": "店铺为何被砸?", "start": 70900, "end": 72140}, {"text": "为此记者找到了负责丁先生商铺片区的工作人员.", "start": 72140, "end": 75560}, {"text": "呃,", "start": 75560, "end": 76180}, {"text": "现在是这样的.", "start": 76180, "end": 77060}, {"text": "呃,", "start": 77060, "end": 77539}, {"text": "第一块呢就是说我们涉及目前的话,", "start": 77539, "end": 79820}, {"text": "就是涉及到呃商铺的这个调整呢,", "start": 79820, "end": 82360}, {"text": "总共是四家.", "start": 82360, "end": 83240}, {"text": "然后呢,", "start": 83240, "end": 84120}, {"text": "其中其他家三家呢,", "start": 84120, "end": 85860}, {"text": "我们都是和平的,", "start": 85860, "end": 86880}, {"text": "就是让呃解决掉了.", "start": 86880, "end": 88380}, {"text": "其实我们甲方一直本着这个呃和平相处的这个这种态度,", "start": 88380, "end": 92560}, {"text": "拿出一些诚意.", "start": 92560, "end": 93460}, {"text": "所以说其他三家呢我们都顺利的就是说已经已经签署了这个相应的解除合同以及正式的这个呃租赁合同.", "start": 93460, "end": 99979}, {"text": "就是比如说普惠的调整啊等等之类的啊,", "start": 99979, "end": 102160}, {"text": "这是其他这是总共涉及到四家那三家的情况.", "start": 102160, "end": 104800}, {"text": "针对呃一德安照相馆丁东这一块呢,", "start": 104800, "end": 107440}, {"text": "就是说那我们呃作为甲方这一块呢,", "start": 107440, "end": 110180}, {"text": "我们的初衷还是想本着这个和平共处以及这个公平公正的这种这这这种态度.", "start": 110180, "end": 116120}, {"text": "然后我们想处理这个事情,", "start": 116120, "end": 117759}, {"text": "然后在于前期呢我们呃也和呃照相馆丁东这边做一个沟通,", "start": 117759, "end": 122910}, {"text": "我们想给他调整一些呃调整个位置,", "start": 122910, "end": 124890}, {"text": "我们们还并不想叫他离开.", "start": 124890, "end": 127350}, {"text": "我们就是说这个场地工作人员告知记者,", "start": 127350, "end": 130410}, {"text": "在双方当初签订的租赁合同上有这样一条规定,", "start": 130410, "end": 133710}, {"text": "即甲方如果以特殊原因提出解除合同需要赔付乙方两个月的房屋租金,", "start": 133710, "end": 139109}, {"text": "现在这笔钱,", "start": 139109, "end": 140430}, {"text": "他们愿意赔付,", "start": 140430, "end": 141390}, {"text": "也愿意赔偿丁先生的装修损失费,", "start": 141390, "end": 143730}, {"text": "但是损失费的金额,", "start": 143730, "end": 145230}, {"text": "双方始终达不成一致.", "start": 145230, "end": 147210}, {"text": "首先我们口头的协商了,", "start": 147210, "end": 149050}, {"text": "下了过之后呢,", "start": 149050, "end": 149950}, {"text": "我们又以纸质版的一一个一个一个告知啊,", "start": 149950, "end": 152890}, {"text": "就是说呃目前的话存在的这个差距差距差距点在哪里呢?", "start": 152890, "end": 157550}, {"text": "就是说呃他这一块的话,", "start": 157550, "end": 159590}, {"text": "当时我们第一次然后交沟通交涉的呃沟通的时候呢,", "start": 159590, "end": 163910}, {"text": "他是呃丁总这一块呢报价是十五万的赔偿啊,", "start": 163910, "end": 167350}, {"text": "然后我们给他由于根据我们甲方的这个这个这个测算.", "start": 167350, "end": 171230}, {"text": "然后的话呢跟我们这个赔偿的这个差距性比较大,", "start": 171230, "end": 174329}, {"text": "然后呢我们就进行第二轮交涉,", "start": 174329, "end": 176370}, {"text": "第二轮交涉呢,", "start": 176370, "end": 177210}, {"text": "丁总这一块呢报价是二十万赔偿.", "start": 177210, "end": 179250}, {"text": "然后那跟我们的差距,", "start": 179250, "end": 180990}, {"text": "那我们们又又又又增大了一点差距.", "start": 180990, "end": 183760}, {"text": "然后第三次我们交涉,", "start": 183760, "end": 185579}, {"text": "然后下了第三次喊丁总这一块报价是二十七万啊.", "start": 185579, "end": 188799}, {"text": "那么跟我们那个甲方,", "start": 188799, "end": 190239}, {"text": "我们是这一块呃,", "start": 190239, "end": 191600}, {"text": "完全不能接受这一块啊,", "start": 191600, "end": 193179}, {"text": "对于他的被砸这一事实,", "start": 193179, "end": 195220}, {"text": "工作人员承认,", "start": 195220, "end": 196060}, {"text": "确实是他们所为丁先生的所有器材.", "start": 196060, "end": 198420}, {"text": "目前他们已经妥善保管,", "start": 198420, "end": 200000}, {"text": "截止涉及到一个赔偿赔偿问题,", "start": 200000, "end": 202339}, {"text": "赔偿问题.", "start": 202339, "end": 202940}, {"text": "他他这一块一直的给我们这个价呃差距比较大,", "start": 202940, "end": 206399}, {"text": "一次是甚至约谈价格越高.", "start": 206399, "end": 208959}, {"text": "我们这样的话对由于时间比较紧,", "start": 208959, "end": 211119}, {"text": "所以说对于外观和损坏呢,", "start": 211119, "end": 213660}, {"text": "这一块呢就是说嗯前期呢我们跟照相管的这块只能呃也在一起沟通,", "start": 213660, "end": 218440}, {"text": "包括他的这个物品呢,", "start": 218440, "end": 220000}, {"text": "这一块呢我们是他这一的就是说呃完好无缝的,", "start": 220000, "end": 223739}, {"text": "然后这一块是给他打包好完好无风的,", "start": 223739, "end": 226260}, {"text": "然后存放在一个合适的一个地方,", "start": 226260, "end": 228100}, {"text": "对现是给他保管的保管好了.", "start": 228100, "end": 230560}, {"text": "截止发稿时,", "start": 230560, "end": 231880}, {"text": "记者了解到,", "start": 231880, "end": 232600}, {"text": "双方仍未就此事达成一致意见,", "start": 232600, "end": 235295}, {"text": "抖音.", "start": 235295, "end": 237395}]}, "ocr_result": [{"frame": 0, "result": [["抖音"], ["抖音号:289393933"], ["协商未果"], ["中泰广场一商铺被砸!"], ["家家悦真棒"], ["业敬"], [""], ["热线追踪"], ["市民丁"], ["说办就办"]]}, {"frame": 15, "result": [["即将开业敬"], ["市民丁先生"], ["我在这个地方租了一个商铺"]]}, {"frame": 30, "result": []}, {"frame": 45, "result": [["家家悦真棉"], ["开业"], ["热线追踪"]]}, {"frame": 75, "result": [["家家悦真"], ["四将开业"], ["说办就"], ["签的合同是三年"]]}, {"frame": 135, "result": [["."], ["印"], ["家家悦真"], ["即将开!"], ["使用期限是到2022年的6月份终止"]]}, {"frame": 195, "result": [["印"], ["但是呢由于商场把我的商铺"], ["抖音"]]}, {"frame": 210, "result": [["市民丁先生"]]}, {"frame": 240, "result": []}, {"frame": 315, "result": [["童链"], ["市民丁先生"], ["就是这个家家悦真棒中泰店"]]}, {"frame": 345, "result": [["家家"], ["TV"], ["即将"]]}, {"frame": 405, "result": [["小黄鹂语言艺术中心"], ["成信"], ["淮北万达由影袖"], ["岩行者攀岩馆"]]}, {"frame": 480, "result": [["记者禹雨薇周涛报道"], ["记者调查:中泰广场商铺被砸"], ["IST"]]}, {"frame": 525, "result": [["中泰国际广场"], ["商铺租赁合同"], [""]]}, {"frame": 570, "result": [["收"], ["8007093"], ["交款单位"], ["F相T"], ["万贰仟壹佰贰拾捌元整"], ["收款方式"], ["9017"], ["8o"], ["杂"], ["201-11-20216301"], ["一品"], [""], ["发"], ["财务专用意"], ["60"], ["抖音"], ["抖音号:289393933"]]}, {"frame": 615, "result": [["协商未果"], ["3."], ["免"]]}, {"frame": 675, "result": [["中泰广场一商铺被砸!"], ["即将开业敬请期待"], ["家家悦真棒中泰店"], ["说办就办"]]}, {"frame": 720, "result": [["南"], ["日"], ["家家悦"], ["即将开"], ["市民"], ["说办就办"], ["因为我搬走呢"], [""]]}, {"frame": 765, "result": [["雅"], ["音KTV"], ["热线追踪"], ["我的装修各方面的损失达到20多万"]]}, {"frame": 990, "result": [[""], ["声音KTV"], ["这肯定是达不到我的损失的"]]}, {"frame": 1065, "result": [["荣园"], ["好声音KTV"], ["市民丁先生"], ["我就要求继续承租这个房屋"]]}, {"frame": 1170, "result": [["上仪式感·照相馆"]]}, {"frame": 1245, "result": [[""], ["仪式"], ["感"], ["照相馆"], ["3"]]}, {"frame": 1335, "result": [[""]]}, {"frame": 1410, "result": [["协商未果的情况下"]]}, {"frame": 1455, "result": [["1"]]}, {"frame": 1530, "result": [["市民丁先生"], ["把我的门砸了"]]}, {"frame": 1590, "result": [["把我的所有装修全部损坏了"]]}, {"frame": 1605, "result": []}, {"frame": 1680, "result": [["然后又把我的东西都拉走了"]]}, {"frame": 1695, "result": []}, {"frame": 1710, "result": []}, {"frame": 1725, "result": []}, {"frame": 1740, "result": [["生"], ["我的店员也没地方上班"]]}, {"frame": 1755, "result": [["说办就办"]]}, {"frame": 1770, "result": []}, {"frame": 1800, "result": [["也无法营业"]]}, {"frame": 1845, "result": [["我现在就要求给我一个公道的说法"]]}, {"frame": 1920, "result": [["式感"]]}, {"frame": 1965, "result": [["文吧"], ["抖音"], ["抖音号:289393933"]]}, {"frame": 1980, "result": [["协商未果"], [""]]}, {"frame": 2055, "result": [["佳北万达电影城"], ["破!"], ["岩行者攀"], [""], ["淮北市中天泰"], ["说办就办"]]}, {"frame": 2070, "result": [["中泰广场一商铺被砸!"], ["城信"], ["岩行者攀爸"], ["就"], ["说办"], ["淮北市中天泰富实业有限公司工作人员"], ["说办就办"], ["现在是这样的"]]}, {"frame": 2130, "result": [["淮北万达电影城"], ["信"], ["城"], ["岩行者"], ["就办"], ["说办"], ["热线追踪"], ["淮北市中天泰富实业有限公司工作人员"], ["第一块我们目前的涉及到商铺的调整"]]}, {"frame": 2145, "result": [["欢力"]]}, {"frame": 2160, "result": [["烤价"], ["超"]]}, {"frame": 2445, "result": [["火锅·烤肉"], ["8"], ["淮北市中天泰富实业有限公司工作人员"], ["和平相处的态度拿出一些诚意"]]}, {"frame": 2490, "result": [["锡·烤肉"], ["就刃"]]}, {"frame": 2580, "result": [["岩行者"], ["所以其他三家都顺利的"]]}, {"frame": 2625, "result": [["破"], ["信"], ["火锅"], ["肉"], ["已经签署了相应的解除合同"]]}, {"frame": 2640, "result": [["烤肉"]]}, {"frame": 2655, "result": [["玻信"], ["岩行者"]]}, {"frame": 2670, "result": []}, {"frame": 2700, "result": [["火锅·"], ["购"]]}, {"frame": 2715, "result": [["还有正式的租赁合同"]]}, {"frame": 2835, "result": [["淮北万达电影城"], ["岩行"], ["那三家的情况"]]}, {"frame": 2865, "result": [["岩行"], ["火罐·纯肉"], ["针对于仪式感照相馆丁总这一块呢"]]}, {"frame": 2970, "result": [["我们作为甲方"], ["抖音"], ["抖音号:289393933"]]}, {"frame": 3045, "result": [["协商未果"], ["成信"], ["淮北市中天泰富实业有限公司工作人员"], ["我们的初衷还是想本着和平共处"]]}, {"frame": 3060, "result": [["以及公平公正的这种态度"]]}, {"frame": 3075, "result": [["被信"], ["抖音"]]}, {"frame": 3495, "result": [["中泰广场一商铺被砸!"], ["中泰国际广场"], ["耳"], ["商铺租赁合同"], [""], ["说办就办"]]}, {"frame": 3525, "result": [["安1水0657.4号10"], ["邱建伟"], ["书半之"], [""], ["350l03197906"], ["13965886655"], ["同"], ["0xt6xx18x"]]}, {"frame": 3585, "result": [["热线追踪"], ["促成"]]}, {"frame": 3675, "result": [["营业执照"], ["记机关"]]}, {"frame": 3720, "result": [["告知函"], ["2020年12"]]}, {"frame": 3750, "result": []}, {"frame": 3765, "result": []}, {"frame": 3780, "result": []}, {"frame": 3810, "result": []}, {"frame": 3825, "result": []}, {"frame": 3840, "result": []}, {"frame": 3855, "result": []}, {"frame": 3885, "result": []}, {"frame": 3900, "result": []}, {"frame": 3915, "result": []}, {"frame": 3930, "result": []}, {"frame": 3975, "result": []}, {"frame": 4770, "result": [["说办就办"], ["我们就进行了第二轮交涉"]]}, {"frame": 4830, "result": [["第二轮丁总的报价是二十万赔偿"]]}, {"frame": 5220, "result": []}, {"frame": 5250, "result": []}, {"frame": 5265, "result": []}, {"frame": 5280, "result": []}, {"frame": 5295, "result": []}, {"frame": 5310, "result": []}, {"frame": 5325, "result": []}, {"frame": 5370, "result": []}, {"frame": 5415, "result": [["淮北万达电影城"], ["岩行者"], ["淮北市中天泰富实业有"], ["还是涉及到赔偿问题"]]}, {"frame": 5460, "result": [["玻位"], ["淮北市中天泰富实业有限公司工作人员"]]}, {"frame": 5580, "result": [["说办就办一次一次甚至越谈价格越高"]]}, {"frame": 5595, "result": []}, {"frame": 5610, "result": [["抖音号:289393933"]]}, {"frame": 5625, "result": [["协商未果"]]}, {"frame": 5640, "result": []}, {"frame": 5655, "result": []}, {"frame": 5670, "result": [["淮北市中天泰富实业有限公司工作人员"], ["我们由于时间比较紧"]]}, {"frame": 5715, "result": [["至于它的这个外观和损坏"], ["抖音"]]}, {"frame": 5730, "result": [["中泰广场一商铺被砸!"], ["上仪式感·照相馆"]]}, {"frame": 5775, "result": [["贼"], ["信"], ["岩行"], ["淮北市中天泰富实业有限公司工作人员"]]}, {"frame": 6240, "result": [["小黄鹂语言艺术中心"], ["时你"], ["说办就办"], ["淮北万达申影城"], ["岩行者摹岩馆"]]}, {"frame": 6300, "result": [["家家悦真棒中泰店"], ["即将开业敬请期待"], ["热线追踪"]]}, {"frame": 6375, "result": [["h"], ["淮北同城会"], ["来抖音"], ["发现更多有趣创作者"], ["抖音号:"], ["289393933"]]}], "fps": 27.0}