{"video_id": "douyin_7044536903693110536", "wav_result": {"text": "各位皮友拉个屎，他妈的房子塌了，吓得我屁股都没擦，就跑出来，我现在被困了，我该怎么办？我好怕开啊。对的，这是光，这是第一层楼就全出来了，高层楼睡在楼上面，我要我要拍拍，让让我。", "text_postprocessed": "各 位 皮 友 拉 个 屎 他 妈 的 房 子 塌 了 吓 得 我 屁 股 都 没 擦 就 跑 出 来 我 现 在 被 困 了 我 该 怎 么 办 我 好 怕 开 啊 对 的 这 是 光 这 是 第 一 层 楼 就 全 出 来 了 高 层 楼 睡 在 楼 上 面 我 要 我 要 拍 拍 让 让 我", "time_stamp": [[810, 950], [950, 1090], [1090, 1250], [1250, 1490], [1970, 2190], [2190, 2310], [2310, 2550], [2630, 2770], [2770, 2950], [2950, 3090], [3090, 3230], [3230, 3410], [3410, 3590], [3590, 3915], [4890, 5130], [5130, 5250], [5250, 5390], [5390, 5529], [5529, 5649], [5649, 5729], [5729, 5830], [5830, 5989], [5989, 6130], [6130, 6289], [6289, 6449], [6449, 6795], [8010, 8150], [8150, 8250], [8250, 8370], [8370, 8450], [8450, 8590], [8590, 8710], [8710, 8790], [8790, 8870], [8870, 8950], [8950, 9030], [9030, 9270], [9850, 10070], [10070, 10230], [10230, 10675], [11620, 11860], [15660, 16044], [16950, 17189], [17310, 17460], [20619, 20700], [20700, 20939], [20959, 21200], [21439, 21599], [21599, 21740], [21740, 21860], [21860, 22040], [22040, 22159], [22159, 22279], [22279, 22479], [22479, 22639], [22639, 22740], [22740, 22840], [22840, 22979], [22979, 23159], [23159, 23279], [23279, 23419], [23419, 23540], [23540, 23680], [23680, 23820], [23820, 24000], [24000, 24375], [25260, 25460], [25460, 25700], [25820, 25980], [25980, 26120], [26120, 26320], [26320, 26560], [26760, 26960], [26960, 27200], [27200, 27645]], "sentences": [{"text": "各位皮友拉个屎,", "start": 810, "end": 2550}, {"text": "他妈的房子塌了,", "start": 2550, "end": 3915}, {"text": "吓得我屁股都没擦,", "start": 3915, "end": 5989}, {"text": "就跑出来,", "start": 5989, "end": 6795}, {"text": "我现在被困了,", "start": 6795, "end": 8710}, {"text": "我该怎么办?", "start": 8710, "end": 9270}, {"text": "我好怕开啊.", "start": 9270, "end": 16044}, {"text": "对的,", "start": 16044, "end": 17460}, {"text": "这是光,", "start": 17460, "end": 21200}, {"text": "这是第一层楼就全出来了,", "start": 21200, "end": 22979}, {"text": "高层楼睡在楼上面,", "start": 22979, "end": 24375}, {"text": "我要我要拍拍,", "start": 24375, "end": 26560}, {"text": "让让我.", "start": 26560, "end": 27645}]}, "ocr_result": [{"frame": 0, "result": []}, {"frame": 15, "result": []}, {"frame": 30, "result": [["各位兄弟"]]}, {"frame": 45, "result": []}, {"frame": 60, "result": [["拉个屎他妈的房子塌了"]]}, {"frame": 75, "result": [["拉个屎他妈的房子塌了"]]}, {"frame": 90, "result": []}, {"frame": 105, "result": []}, {"frame": 120, "result": [["吓得我屁股都没擦就跑出来了"]]}, {"frame": 135, "result": []}, {"frame": 150, "result": []}, {"frame": 165, "result": [["吓得我屁股都没擦就跑出来了"]]}, {"frame": 180, "result": []}, {"frame": 195, "result": [["我现在被困了我该怎么办"]]}, {"frame": 210, "result": []}, {"frame": 225, "result": [["我现在被困了我该怎么办"]]}, {"frame": 240, "result": [["我好怕"]]}, {"frame": 255, "result": []}, {"frame": 270, "result": []}, {"frame": 285, "result": [["2021年12月22日星期三21:46:20"], ["鸡棚"]]}, {"frame": 480, "result": []}, {"frame": 495, "result": [["这些低层楼就"], ["全出来了"]]}, {"frame": 525, "result": []}, {"frame": 540, "result": []}, {"frame": 555, "result": [["5"], ["高层楼的还在楼上"]]}, {"frame": 570, "result": [["9m"]]}, {"frame": 585, "result": []}, {"frame": 600, "result": []}, {"frame": 615, "result": [["太可怕了"]]}, {"frame": 630, "result": []}, {"frame": 645, "result": []}, {"frame": 660, "result": []}, {"frame": 675, "result": []}, {"frame": 690, "result": []}, {"frame": 705, "result": []}], "fps": 24.0}