{"video_id": "douyin_6922285670010473740", "wav_result": {"text": "犹豫买回来了，现在时间是五分半看一下没了，已经有差不多六分钟了，家都没有了，抖音。", "text_postprocessed": "犹 豫 买 回 来 了 现 在 时 间 是 五 分 半 看 一 下 没 了 已 经 有 差 不 多 六 分 钟 了 家 都 没 有 了 抖 音", "time_stamp": [[300, 440], [440, 640], [640, 780], [780, 960], [960, 1060], [1060, 1265], [3630, 3849], [3849, 4070], [4070, 4310], [4310, 4529], [4529, 4770], [4810, 5050], [5050, 5290], [5290, 5645], [6210, 6330], [6330, 6470], [6470, 6685], [7900, 8140], [8140, 8380], [8820, 8980], [8980, 9220], [9280, 9520], [9640, 9800], [9800, 9880], [9880, 9980], [9980, 10080], [10080, 10260], [10260, 10380], [10380, 10620], [10920, 11140], [11140, 11280], [11280, 11380], [11380, 11560], [11560, 11825], [13270, 13510], [13570, 14055]], "sentences": [{"text": "犹豫买回来了,", "start": 300, "end": 1265}, {"text": "现在时间是五分半看一下没了,", "start": 1265, "end": 8380}, {"text": "已经有差不多六分钟了,", "start": 8380, "end": 10620}, {"text": "家都没有了,", "start": 10620, "end": 11825}, {"text": "抖音.", "start": 11825, "end": 14055}]}, "ocr_result": [{"frame": 0, "result": [["料音"], ["小鱼视频"], ["抖音号:fishclip"], ["女子将鱿鱼放水里"], ["煮着煮着就没了"], ["网友:"], ["买了个寂寞?"], [":"], ["1月26日"], ["四川成都"], ["鱿鱼买回来了"]]}, {"frame": 15, "result": [["d"], ["抖音"], ["抖音号:"], ["fishclip"], ["鱿鱼买回来了"]]}, {"frame": 60, "result": [["d。"], ["抖音号:"], ["女子将鱿鱼放水里"], ["煮着煮着就没了"], ["网友:"], ["买了个寂寞?"], ["1月26日"]]}, {"frame": 75, "result": [["女子将鱿鱼放水里"], ["买了个寂寞?"], [":"], ["1月26日"], ["四川成都"]]}, {"frame": 90, "result": [["抖音"]]}, {"frame": 105, "result": [["煮着煮着就没了"], ["保险"], ["买了个寂寞?"], ["60"], ["45"], ["05:35.10"], ["现在时间是五分半"], [""], ["世界时钟"], ["计时尚"]]}, {"frame": 135, "result": [["女子将鱿鱼放水里"], ["保险"], ["买了个寂寞?"], ["60"], ["11"], ["15"], ["世界过钟"], ["计时器"]]}, {"frame": 165, "result": [["煮着煮着就没了"], ["现在时间是五分半"], ["//"], ["抖音号: fishclip"]]}, {"frame": 180, "result": [["然后看一下"]]}, {"frame": 195, "result": [["女子将鱿鱼放水里"], ["煮着煮着就没了"], ["然后看一下"], ["抖音"]]}, {"frame": 210, "result": [["抖音号: fishclip"]]}, {"frame": 225, "result": [["买了个寂寞?"], [":"], ["抖音号: fishclip"]]}, {"frame": 240, "result": [["1月26日"], ["没了"], ["抖音"]]}, {"frame": 255, "result": [["小鱼视频"], ["d"]]}, {"frame": 270, "result": [["已经有差不多6分钟了"]]}, {"frame": 300, "result": [["已经有差不多6分钟了"], ["抖音"]]}, {"frame": 315, "result": [[":"], ["四川成都"]]}, {"frame": 330, "result": [["渣都没有了"]]}, {"frame": 345, "result": []}, {"frame": 360, "result": [[":"]]}, {"frame": 375, "result": [["小鱼视频"], ["来抖音"], ["发现更多有趣创作者"], [""]]}], "fps": 30.0}